{
  "main_contents" : {
    "first_banner_list" : {
      "title" : null,
      "sub_title" : null,
      "banner_list" : {
        "items" : [ {
          "banner_nm" : "캐주얼부터 로맨틱까지,<br>데일리룩 완전정복!!",
          "img_url" : "http://image.lotte.com/goods/58/02/53/93/3/393530258_1_550.jpg",
          "img_link" : "/planshop/viewPlanShopDetail.lotte?spdp_no=5380227",
          "goods_no" : 393530258,
          "sold_out" : false,
          "price" : "17790",
          "brnd_nm" : "핑크시슬리",
          "bg_color" : "#C07F5A",
          "url_link" : null
        }, {
          "banner_nm" : "누구나 매력적으로 <br> 변신할 수 있는 찬스!",
          "img_url" : "http://image.lotte.com/goods/25/98/91/76/1/176919825_2_550.jpg",
          "img_link" : "/planshop/viewPlanShopDetail.lotte?spdp_no=5400388",
          "goods_no" : 176919825,
          "sold_out" : false,
          "price" : "13600",
          "brnd_nm" : "임블리(imvely)",
          "bg_color" : "#CC723D",
          "url_link" : null
        }, {
          "banner_nm" : "신규브랜드 입점 행사, <br> 아침부터 밤까지 완벽하게♥",
          "img_url" : "http://image.lotte.com/goods/72/60/80/06/4/406806072_1_550.jpg",
          "img_link" : "/planshop/viewPlanShopDetail.lotte?spdp_no=5412168",
          "goods_no" : 406806072,
          "sold_out" : false,
          "price" : "10530",
          "brnd_nm" : "립합(LIPHOP)",
          "bg_color" : "#6799FF",
          "url_link" : null
        }, {
          "banner_nm" : "데일리룩도 사랑스럽고 <BR> 로맨틱하게♥",
          "img_url" : "http://image.lotte.com/goods/98/53/22/80/1/180225398_1_550.jpg",
          "img_link" : "/planshop/viewPlanShopDetail.lotte?spdp_no=5365060",
          "goods_no" : 180225398,
          "sold_out" : false,
          "price" : "7920",
          "brnd_nm" : "톰앤래빗",
          "bg_color" : "#BD9424",
          "url_link" : null
        }, {
          "banner_nm" : "인기 스타일  <BR> 다 모였다★",
          "img_url" : "http://image.lotte.com/goods/68/71/56/03/3/303567168_7_550.jpg",
          "img_link" : "/planshop/viewPlanShopDetail.lotte?spdp_no=5338890",
          "goods_no" : 303567168,
          "sold_out" : false,
          "price" : "6900",
          "brnd_nm" : "스타일온미",
          "bg_color" : "#E0844F",
          "url_link" : null
        } ],
        "total_count" : 5
      },
      "hash_list" : null
    },
    "keyword_list" : {
      "title" : "HOT KEYWORD",
      "sub_title" : "지금 이 시간! <br>주목받는 \u0027실검랭킹\u0027",
      "banner_list" : {
        "items" : [ {
          "banner_nm" : "린넨원피스",
          "img_url" : "http://image.lotte.com/goods/35/52/76/74/3/374765235_1_280.jpg",
          "img_link" : "/planshop/viewPlanShopDetail.lotte?spdp_no=5409117",
          "goods_no" : 374765235,
          "sold_out" : false,
          "price" : "26990",
          "brnd_nm" : "저스트원",
          "bg_color" : "",
          "url_link" : null
        }, {
          "banner_nm" : "원피스",
          "img_url" : "http://image.lotte.com/goods/58/30/39/92/3/392393058_1_280.jpg",
          "img_link" : "/planshop/viewPlanShopDetail.lotte?spdp_no=5409116",
          "goods_no" : 392393058,
          "sold_out" : false,
          "price" : "41110",
          "brnd_nm" : "제이스타일",
          "bg_color" : "",
          "url_link" : null
        }, {
          "banner_nm" : "로브가디건",
          "img_url" : "http://image.lotte.com/goods/25/83/61/90/3/390618325_1_280.jpg",
          "img_link" : "5578006",
          "goods_no" : 390618325,
          "sold_out" : false,
          "price" : "35030",
          "brnd_nm" : "끌로드마농",
          "bg_color" : "",
          "url_link" : null
        }, {
          "banner_nm" : "점프수트",
          "img_url" : "http://image.lotte.com/goods/78/22/36/00/4/400362278_1_280.jpg",
          "img_link" : "5550719",
          "goods_no" : 400362278,
          "sold_out" : false,
          "price" : "61520",
          "brnd_nm" : "업타운홀릭",
          "bg_color" : "",
          "url_link" : null
        }, {
          "banner_nm" : "블라우스",
          "img_url" : "http://image.lotte.com/goods/60/79/68/75/3/375687960_1_280.jpg",
          "img_link" : "5550671",
          "goods_no" : 375687960,
          "sold_out" : false,
          "price" : "30690",
          "brnd_nm" : "피오나",
          "bg_color" : "",
          "url_link" : null
        }, {
          "banner_nm" : "오프숄더",
          "img_url" : "http://image.lotte.com/goods/62/49/36/00/4/400364962_1_280.jpg",
          "img_link" : "5550659",
          "goods_no" : 400364962,
          "sold_out" : false,
          "price" : "24180",
          "brnd_nm" : "블랑조",
          "bg_color" : "",
          "url_link" : null
        }, {
          "banner_nm" : "뷔스티에 원피스",
          "img_url" : "http://image.lotte.com/goods/31/08/56/03/4/403560831_1_280.jpg",
          "img_link" : "5573173",
          "goods_no" : 403560831,
          "sold_out" : false,
          "price" : "27720",
          "brnd_nm" : "톰앤래빗",
          "bg_color" : "",
          "url_link" : null
        } ],
        "total_count" : 7
      },
      "hash_list" : null
    },
    "best_list" : {
      "title" : "BEST ITEM",
      "sub_title" : "어머! 이건 사야해!!! <br> 지갑열리게 하는 아이템",
      "banner_list" : {
        "items" : [ {
          "banner_nm" : "저스트원",
          "img_url" : "http://image.lotte.com/goods/09/19/29/94/3/394291909_1_550.jpg",
          "img_link" : "",
          "goods_no" : 394291909,
          "sold_out" : false,
          "price" : "21220",
          "brnd_nm" : "데일리 린넨 <BR>\n반오픈 원피스",
          "bg_color" : "",
          "url_link" : null
        }, {
          "banner_nm" : "비나인",
          "img_url" : "http://image.lotte.com/goods/47/12/92/65/3/365921247_1_550.jpg",
          "img_link" : "",
          "goods_no" : 365921247,
          "sold_out" : false,
          "price" : "28300",
          "brnd_nm" : "베스트 아이템★<BR>\n오버사이즈 OPS",
          "bg_color" : "",
          "url_link" : null
        }, {
          "banner_nm" : "블랑조",
          "img_url" : "http://image.lotte.com/goods/19/68/04/89/3/389046819_1_550.jpg",
          "img_link" : "",
          "goods_no" : 389046819,
          "sold_out" : false,
          "price" : "17790",
          "brnd_nm" : "센스만점, 휴양지 <BR>\n에스닉 로브 가디건",
          "bg_color" : "",
          "url_link" : null
        }, {
          "banner_nm" : "임블리(imvely)",
          "img_url" : "http://image.lotte.com/goods/46/80/82/05/4/405828046_1_550.jpg",
          "img_link" : "",
          "goods_no" : 405828046,
          "sold_out" : false,
          "price" : "42840",
          "brnd_nm" : "요리 봐도 조리 봐도<BR>\n♥사랑스러워♥",
          "bg_color" : "",
          "url_link" : null
        }, {
          "banner_nm" : "화이트폭스",
          "img_url" : "http://image.lotte.com/goods/68/47/87/06/4/406874768_1_550.jpg",
          "img_link" : "",
          "goods_no" : 406874768,
          "sold_out" : false,
          "price" : "24360",
          "brnd_nm" : "반전 원피스!! <BR>\n백라인 스트랩 OPS",
          "bg_color" : "",
          "url_link" : null
        }, {
          "banner_nm" : "제이스타일",
          "img_url" : "http://image.lotte.com/goods/55/97/46/06/4/406469755_1_550.jpg",
          "img_link" : "",
          "goods_no" : 406469755,
          "sold_out" : false,
          "price" : "18700",
          "brnd_nm" : "여행지에서도 <BR>\n귀엽게,멋스럽게~!",
          "bg_color" : "",
          "url_link" : null
        }, {
          "banner_nm" : "톰앤래빗",
          "img_url" : "http://image.lotte.com/goods/54/26/29/86/3/386292654_1_550.jpg",
          "img_link" : "",
          "goods_no" : 386292654,
          "sold_out" : false,
          "price" : "17600",
          "brnd_nm" : "페미닌한 무드를  <BR>\n전해주는 스커트",
          "bg_color" : "",
          "url_link" : null
        }, {
          "banner_nm" : "립합(LIPHOP)",
          "img_url" : "http://image.lotte.com/goods/98/95/38/05/4/405389598_1_550.jpg",
          "img_link" : "",
          "goods_no" : 405389598,
          "sold_out" : false,
          "price" : "16380",
          "brnd_nm" : "은근한 섹시미를 <BR>\n자랑하는 탑 원피스",
          "bg_color" : "",
          "url_link" : null
        } ],
        "total_count" : 8
      },
      "hash_list" : [ {
        "hash_nm" : "데이트룩시피",
        "ctg_no" : "/planshop/viewPlanShopDetail.lotte?spdp_no=5407153"
      }, {
        "hash_nm" : "오프숄더",
        "ctg_no" : "5550659"
      }, {
        "hash_nm" : "뷔스티에 원피스",
        "ctg_no" : "5573173"
      }, {
        "hash_nm" : "플라워",
        "ctg_no" : "5552854"
      }, {
        "hash_nm" : "부츠컷",
        "ctg_no" : "5552384"
      }, {
        "hash_nm" : "점프수트",
        "ctg_no" : "5550719"
      } ]
    },
    "theme_list_1" : {
      "title" : "롱 원피스 하나로 ",
      "sub_title" : "휴가지에서도 <br> 패셔니스타로 거듭나자!!",
      "banner_list" : {
        "items" : [ {
          "banner_nm" : "데이지 맥시 원피스",
          "img_url" : "http://image.lotte.com/goods/38/52/76/74/3/374765238_1_280.jpg",
          "img_link" : "-",
          "goods_no" : 374765238,
          "sold_out" : false,
          "price" : "12250",
          "brnd_nm" : "저스트원",
          "bg_color" : "",
          "url_link" : null
        }, {
          "banner_nm" : "레이스 원피스set",
          "img_url" : "http://image.lotte.com/goods/27/40/08/89/3/389084027_1_280.jpg",
          "img_link" : "-",
          "goods_no" : 389084027,
          "sold_out" : false,
          "price" : "23330",
          "brnd_nm" : "블랑조",
          "bg_color" : "",
          "url_link" : null
        }, {
          "banner_nm" : "에스닉 롱 OPS",
          "img_url" : "http://image.lotte.com/goods/43/59/87/64/2/264875943_1_280.jpg",
          "img_link" : "-",
          "goods_no" : 264875943,
          "sold_out" : false,
          "price" : "22080",
          "brnd_nm" : "이니크",
          "bg_color" : "",
          "url_link" : null
        }, {
          "banner_nm" : "X끈트임원피스 ",
          "img_url" : "http://image.lotte.com/goods/23/37/51/85/3/385513723_1_280.jpg",
          "img_link" : "-",
          "goods_no" : 385513723,
          "sold_out" : false,
          "price" : "22320",
          "brnd_nm" : "톰앤래빗",
          "bg_color" : "",
          "url_link" : null
        }, {
          "banner_nm" : "히아플라이 ops ",
          "img_url" : "http://image.lotte.com/goods/17/42/02/99/3/399024217_1_280.jpg",
          "img_link" : "-",
          "goods_no" : 399024217,
          "sold_out" : false,
          "price" : "60720",
          "brnd_nm" : "업타운홀릭",
          "bg_color" : "",
          "url_link" : null
        }, {
          "banner_nm" : "타이머 단가라 민소매 밴딩 원피스",
          "img_url" : "http://image.lotte.com/goods/39/69/27/60/2/260276939_1_280.jpg",
          "img_link" : "-",
          "goods_no" : 260276939,
          "sold_out" : false,
          "price" : "14220",
          "brnd_nm" : "디에이스",
          "bg_color" : "",
          "url_link" : null
        }, {
          "banner_nm" : "애슬 롱 랩핑 원피스",
          "img_url" : "http://image.lotte.com/goods/19/94/85/06/4/406859419_1_280.jpg",
          "img_link" : "-",
          "goods_no" : 406859419,
          "sold_out" : false,
          "price" : "16950",
          "brnd_nm" : "피핀",
          "bg_color" : "",
          "url_link" : null
        }, {
          "banner_nm" : "네이블 수술 롱원피스",
          "img_url" : "http://image.lotte.com/goods/19/62/27/64/3/364276219_1_280.jpg",
          "img_link" : "-",
          "goods_no" : 364276219,
          "sold_out" : false,
          "price" : "20520",
          "brnd_nm" : "핑크시슬리",
          "bg_color" : "#C97171",
          "url_link" : null
        }, {
          "banner_nm" : "온더리버 마디롱린넨원피스",
          "img_url" : "http://image.lotte.com/goods/11/25/09/95/3/395092511_1_280.jpg",
          "img_link" : "-",
          "goods_no" : 395092511,
          "sold_out" : false,
          "price" : "27210",
          "brnd_nm" : "온더리버",
          "bg_color" : "",
          "url_link" : null
        }, {
          "banner_nm" : "변하지않을거야 맥시드레스",
          "img_url" : "http://image.lotte.com/goods/81/99/60/96/3/396609981_1_280.jpg",
          "img_link" : "-",
          "goods_no" : 396609981,
          "sold_out" : false,
          "price" : "14360",
          "brnd_nm" : "큐니걸스",
          "bg_color" : "",
          "url_link" : null
        }, {
          "banner_nm" : "멜로딘원피스",
          "img_url" : "http://image.lotte.com/goods/47/62/95/97/3/397956247_1_280.jpg",
          "img_link" : "-",
          "goods_no" : 397956247,
          "sold_out" : false,
          "price" : "20460",
          "brnd_nm" : "톰앤래빗",
          "bg_color" : "",
          "url_link" : null
        }, {
          "banner_nm" : "Soft crease check one-piece",
          "img_url" : "http://image.lotte.com/goods/60/92/74/76/3/376749260_1_280.jpg",
          "img_link" : "-",
          "goods_no" : 376749260,
          "sold_out" : false,
          "price" : "38610",
          "brnd_nm" : "데일리먼데이",
          "bg_color" : "",
          "url_link" : null
        }, {
          "banner_nm" : "하난 홀터넥 밴딩 ops",
          "img_url" : "http://image.lotte.com/goods/14/99/42/92/3/392429914_1_280.jpg",
          "img_link" : "-",
          "goods_no" : 392429914,
          "sold_out" : false,
          "price" : "9990",
          "brnd_nm" : "뽀람",
          "bg_color" : "",
          "url_link" : null
        }, {
          "banner_nm" : "하와이안랩자켓",
          "img_url" : "http://image.lotte.com/goods/44/63/87/85/3/385876344_1_280.jpg",
          "img_link" : "-",
          "goods_no" : 385876344,
          "sold_out" : false,
          "price" : "25600",
          "brnd_nm" : "톰앤래빗",
          "bg_color" : "",
          "url_link" : null
        }, {
          "banner_nm" : "롱 뷔스티에 원피스",
          "img_url" : "http://image.lotte.com/goods/22/13/66/97/3/397661322_1_280.jpg",
          "img_link" : "-",
          "goods_no" : 397661322,
          "sold_out" : false,
          "price" : "29100",
          "brnd_nm" : "블랑조",
          "bg_color" : "",
          "url_link" : null
        }, {
          "banner_nm" : "소이다 날개소매 롱원피스",
          "img_url" : "http://image.lotte.com/goods/41/58/53/93/3/393535841_1_280.jpg",
          "img_link" : "-",
          "goods_no" : 393535841,
          "sold_out" : false,
          "price" : "22310",
          "brnd_nm" : "소이다",
          "bg_color" : "",
          "url_link" : null
        }, {
          "banner_nm" : "홀터린넨원피스",
          "img_url" : "http://image.lotte.com/goods/11/71/08/96/3/396087111_1_280.jpg",
          "img_link" : "-",
          "goods_no" : 396087111,
          "sold_out" : false,
          "price" : "23200",
          "brnd_nm" : "톰앤래빗",
          "bg_color" : "",
          "url_link" : null
        }, {
          "banner_nm" : "깅엄볼륨원피스",
          "img_url" : "http://image.lotte.com/goods/06/03/09/02/4/402090306_1_280.jpg",
          "img_link" : "-",
          "goods_no" : 402090306,
          "sold_out" : false,
          "price" : "51350",
          "brnd_nm" : "쇼룸",
          "bg_color" : "",
          "url_link" : null
        }, {
          "banner_nm" : "뮤즈홀릭 스퀘어린넨롱원피스",
          "img_url" : "http://image.lotte.com/goods/77/88/63/90/3/390638877_1_280.jpg",
          "img_link" : "-",
          "goods_no" : 390638877,
          "sold_out" : false,
          "price" : "48440",
          "brnd_nm" : "일칠사",
          "bg_color" : "",
          "url_link" : null
        }, {
          "banner_nm" : "베리언 나시원피스",
          "img_url" : "http://image.lotte.com/goods/36/78/67/56/2/256677836_1_280.jpg",
          "img_link" : "-",
          "goods_no" : 256677836,
          "sold_out" : false,
          "price" : "12800",
          "brnd_nm" : "핑크시슬리",
          "bg_color" : "",
          "url_link" : null
        } ],
        "total_count" : 20
      },
      "hash_list" : [ ]
    },
    "theme_list_2" : {
      "title" : "베스트 잇템",
      "sub_title" : "애쓰지 않아도 감각적인 <br> 스타일을 더해주는 로브가디건★",
      "banner_list" : {
        "items" : [ {
          "banner_nm" : "에스닉 롱 로브 가디건",
          "img_url" : "http://image.lotte.com/goods/19/68/04/89/3/389046819_1_280.jpg",
          "img_link" : "-",
          "goods_no" : 389046819,
          "sold_out" : false,
          "price" : "17790",
          "brnd_nm" : "블랑조",
          "bg_color" : "",
          "url_link" : null
        }, {
          "banner_nm" : "PALM BOBE 팜 로브",
          "img_url" : "http://image.lotte.com/goods/11/14/87/77/3/377871411_1_280.jpg",
          "img_link" : "-",
          "goods_no" : 377871411,
          "sold_out" : false,
          "price" : "42230",
          "brnd_nm" : "모노마일",
          "bg_color" : "",
          "url_link" : null
        }, {
          "banner_nm" : "롱페이즐리로브",
          "img_url" : "http://image.lotte.com/goods/68/65/36/05/4/405366568_1_280.jpg",
          "img_link" : "-",
          "goods_no" : 405366568,
          "sold_out" : false,
          "price" : "38610",
          "brnd_nm" : "립합(LIPHOP)",
          "bg_color" : "",
          "url_link" : null
        }, {
          "banner_nm" : "플라워자수로브가디건",
          "img_url" : "http://image.lotte.com/goods/89/74/41/94/3/394417489_1_280.jpg",
          "img_link" : "-",
          "goods_no" : 394417489,
          "sold_out" : false,
          "price" : "25500",
          "brnd_nm" : "레드오핀",
          "bg_color" : "",
          "url_link" : null
        }, {
          "banner_nm" : "파인애플 로브",
          "img_url" : "http://image.lotte.com/goods/24/98/06/98/3/398069824_1_280.jpg",
          "img_link" : "-",
          "goods_no" : 398069824,
          "sold_out" : false,
          "price" : "30720",
          "brnd_nm" : "탐나나",
          "bg_color" : "",
          "url_link" : null
        }, {
          "banner_nm" : "썸머 로브가디건",
          "img_url" : "http://image.lotte.com/goods/91/11/69/97/3/397691191_1_280.jpg",
          "img_link" : "-",
          "goods_no" : 397691191,
          "sold_out" : false,
          "price" : "15330",
          "brnd_nm" : "아이엠쓰리",
          "bg_color" : "",
          "url_link" : null
        }, {
          "banner_nm" : "엘레강 플라워 로브가디건",
          "img_url" : "http://image.lotte.com/goods/89/11/69/97/3/397691189_1_280.jpg",
          "img_link" : "-",
          "goods_no" : 397691189,
          "sold_out" : false,
          "price" : "12860",
          "brnd_nm" : "아이엠쓰리",
          "bg_color" : "",
          "url_link" : null
        }, {
          "banner_nm" : "스프링 로브가디건",
          "img_url" : "http://image.lotte.com/goods/88/11/69/97/3/397691188_1_280.jpg",
          "img_link" : "-",
          "goods_no" : 397691188,
          "sold_out" : false,
          "price" : "15330",
          "brnd_nm" : "아이엠쓰리",
          "bg_color" : "",
          "url_link" : null
        }, {
          "banner_nm" : "우연같이만나 로브",
          "img_url" : "http://image.lotte.com/goods/89/11/88/93/3/393881189_1_280.jpg",
          "img_link" : "-",
          "goods_no" : 393881189,
          "sold_out" : false,
          "price" : "18880",
          "brnd_nm" : "큐니걸스",
          "bg_color" : "",
          "url_link" : null
        }, {
          "banner_nm" : "메이빌로브",
          "img_url" : "http://image.lotte.com/goods/41/96/32/00/4/400329641_1_280.jpg",
          "img_link" : "-",
          "goods_no" : 400329641,
          "sold_out" : false,
          "price" : "50700",
          "brnd_nm" : "립합(LIPHOP)",
          "bg_color" : "",
          "url_link" : null
        }, {
          "banner_nm" : "코코플라워로브",
          "img_url" : "http://image.lotte.com/goods/97/33/51/85/3/385513397_1_280.jpg",
          "img_link" : "-",
          "goods_no" : 385513397,
          "sold_out" : false,
          "price" : "31840",
          "brnd_nm" : "톰앤래빗",
          "bg_color" : "",
          "url_link" : null
        }, {
          "banner_nm" : "눈부신야경 로브",
          "img_url" : "http://image.lotte.com/goods/10/46/78/00/4/400784610_1_280.jpg",
          "img_link" : "-",
          "goods_no" : 400784610,
          "sold_out" : false,
          "price" : "11240",
          "brnd_nm" : "큐니걸스",
          "bg_color" : "",
          "url_link" : null
        }, {
          "banner_nm" : "온리플라워 로브",
          "img_url" : "http://image.lotte.com/goods/88/31/19/88/3/388193188_1_280.jpg",
          "img_link" : "-",
          "goods_no" : 388193188,
          "sold_out" : false,
          "price" : "35520",
          "brnd_nm" : "탐나나",
          "bg_color" : "",
          "url_link" : null
        }, {
          "banner_nm" : "잎사귀 로브 가디건(2color)",
          "img_url" : "http://image.lotte.com/goods/00/29/72/88/3/388722900_1_280.jpg",
          "img_link" : "-",
          "goods_no" : 388722900,
          "sold_out" : false,
          "price" : "24070",
          "brnd_nm" : "뽄재이",
          "bg_color" : "",
          "url_link" : null
        }, {
          "banner_nm" : "플라워테잎로브가디건",
          "img_url" : "http://image.lotte.com/goods/91/10/52/89/3/389521091_1_280.jpg",
          "img_link" : "-",
          "goods_no" : 389521091,
          "sold_out" : false,
          "price" : "13500",
          "brnd_nm" : "레드오핀",
          "bg_color" : "",
          "url_link" : null
        }, {
          "banner_nm" : "디쉬플라워로브 ",
          "img_url" : "http://image.lotte.com/goods/18/95/30/71/3/371309518_1_280.jpg",
          "img_link" : "-",
          "goods_no" : 371309518,
          "sold_out" : false,
          "price" : "48260",
          "brnd_nm" : "쉬즈컴잉",
          "bg_color" : "",
          "url_link" : null
        }, {
          "banner_nm" : "야자수나무 나염로브",
          "img_url" : "http://image.lotte.com/goods/45/95/16/95/3/395169545_1_280.jpg",
          "img_link" : "-",
          "goods_no" : 395169545,
          "sold_out" : false,
          "price" : "17010",
          "brnd_nm" : "끌로드마농",
          "bg_color" : "",
          "url_link" : null
        }, {
          "banner_nm" : "필모어 플라워 로브가디건",
          "img_url" : "http://image.lotte.com/goods/89/41/62/90/3/390624189_1_280.jpg",
          "img_link" : "-",
          "goods_no" : 390624189,
          "sold_out" : false,
          "price" : "42050",
          "brnd_nm" : "제이스타일",
          "bg_color" : "",
          "url_link" : null
        }, {
          "banner_nm" : "스카이 빅사이즈 롱나염 로브",
          "img_url" : "http://image.lotte.com/goods/94/70/35/99/3/399357094_1_280.jpg",
          "img_link" : "-",
          "goods_no" : 399357094,
          "sold_out" : false,
          "price" : "28650",
          "brnd_nm" : "임부복닷컴",
          "bg_color" : "",
          "url_link" : null
        }, {
          "banner_nm" : "스트링랩로브",
          "img_url" : "http://image.lotte.com/goods/69/62/48/91/3/391486269_1_280.jpg",
          "img_link" : "-",
          "goods_no" : 391486269,
          "sold_out" : false,
          "price" : "17380",
          "brnd_nm" : "쇼룸",
          "bg_color" : "",
          "url_link" : null
        } ],
        "total_count" : 20
      },
      "hash_list" : [ ]
    },
    "new_prd_list" : {
      "title" : " NEW LOOK",
      "sub_title" : "넘나 이뻐서 기절할 뻔!!!<br>구매욕구 마구 솟는 신상템!!",
      "banner_list" : {
        "items" : [ {
          "banner_nm" : "끌로드마농",
          "img_url" : "http://image.lotte.com/goods/77/15/00/04/4/404001577_1_550.jpg",
          "img_link" : "",
          "goods_no" : 404001577,
          "sold_out" : false,
          "price" : "13500",
          "brnd_nm" : "활용도 높은 <br>\n데일리 나시\n",
          "bg_color" : "",
          "url_link" : null
        }, {
          "banner_nm" : "이니크",
          "img_url" : "http://image.lotte.com/goods/17/62/03/04/4/404036217_1_550.jpg",
          "img_link" : "",
          "goods_no" : 404036217,
          "sold_out" : false,
          "price" : "22550",
          "brnd_nm" : "빈티지한 감성이 <br>\n멋스러운 아이템",
          "bg_color" : "",
          "url_link" : null
        }, {
          "banner_nm" : "데일리먼데이",
          "img_url" : "http://image.lotte.com/goods/72/90/06/04/4/404069072_1_550.jpg",
          "img_link" : "",
          "goods_no" : 404069072,
          "sold_out" : false,
          "price" : "36820",
          "brnd_nm" : "트랜디함이 보여지는 <br>\n와이드 데님 팬츠\n",
          "bg_color" : "",
          "url_link" : null
        }, {
          "banner_nm" : "탐나나",
          "img_url" : "http://image.lotte.com/goods/33/56/74/05/4/405745633_1_550.jpg",
          "img_link" : "",
          "goods_no" : 405745633,
          "sold_out" : false,
          "price" : "35700",
          "brnd_nm" : "빈티지한 트임 디테일이 <br> 멋스러운 데님팬츠",
          "bg_color" : "",
          "url_link" : null
        }, {
          "banner_nm" : "지지배지롱",
          "img_url" : "http://image.lotte.com/goods/61/78/29/05/4/405297861_1_550.jpg",
          "img_link" : "",
          "goods_no" : 405297861,
          "sold_out" : false,
          "price" : "36790",
          "brnd_nm" : "매력적인 패턴이 <br>돋보이는 원피스",
          "bg_color" : "",
          "url_link" : null
        }, {
          "banner_nm" : "큐니걸스",
          "img_url" : "http://image.lotte.com/goods/11/14/33/05/4/405331411_1_550.jpg",
          "img_link" : "",
          "goods_no" : 405331411,
          "sold_out" : false,
          "price" : "20210",
          "brnd_nm" : "클래식한 감성과 <br> 그리너리의 만남",
          "bg_color" : "",
          "url_link" : null
        }, {
          "banner_nm" : "미미앤디디",
          "img_url" : "http://image.lotte.com/goods/74/67/12/03/4/403126774_1_550.jpg",
          "img_link" : "",
          "goods_no" : 403126774,
          "sold_out" : false,
          "price" : "35190",
          "brnd_nm" : "패턴에서 느껴지는 <br>\n특별함이 있는  롱스커트",
          "bg_color" : "",
          "url_link" : null
        }, {
          "banner_nm" : "어썸",
          "img_url" : "http://image.lotte.com/goods/89/58/03/03/4/403035889_1_550.jpg",
          "img_link" : "",
          "goods_no" : 403035889,
          "sold_out" : false,
          "price" : "39900",
          "brnd_nm" : "로맨틱한 실루엣을 <br>\n만들어 줄 맥시 랩 원피스",
          "bg_color" : "",
          "url_link" : null
        } ],
        "total_count" : 8
      },
      "hash_list" : [ {
        "hash_nm" : "임블리X루미씨X탐나나 스타일 레시피",
        "ctg_no" : "/planshop/viewPlanShopDetail.lotte?spdp_no=5400388"
      }, {
        "hash_nm" : "비치웨어",
        "ctg_no" : "5551100"
      }, {
        "hash_nm" : "스트라이프",
        "ctg_no" : "5552446"
      }, {
        "hash_nm" : "데님스커트",
        "ctg_no" : "5550753"
      }, {
        "hash_nm" : "캐주얼세트",
        "ctg_no" : "5550679"
      }, {
        "hash_nm" : "체크",
        "ctg_no" : "5552354"
      } ]
    },
    "last_banner_list" : {
      "title" : null,
      "sub_title" : null,
      "banner_list" : {
        "items" : [ {
          "banner_nm" : "취향저격 <BR> 비치웨어 모음전♥",
          "img_url" : "http://image.lotte.com/goods/39/29/09/95/3/395092939_5_550.jpg",
          "img_link" : "http://www.lotte.com/goods/viewGoodsDetail.lotte?goods_no=395092939",
          "goods_no" : 395092939,
          "sold_out" : false,
          "price" : "8120",
          "brnd_nm" : "화이트폭스",
          "bg_color" : "#CF6E36",
          "url_link" : null
        } ],
        "total_count" : 1
      },
      "hash_list" : null
    },
    "theme_list_3" : {
      "title" : "눈을 어디다 둬야 할지~",
      "sub_title" : "청순과 섹시가 공존하는<BR> 관능미 폭발하는 스타일★",
      "banner_list" : {
        "items" : [ {
          "banner_nm" : "날씬한홀터나시",
          "img_url" : "http://image.lotte.com/goods/21/23/01/04/4/404012321_1_280.jpg",
          "img_link" : "-",
          "goods_no" : 404012321,
          "sold_out" : false,
          "price" : "10920",
          "brnd_nm" : "립합(LIPHOP)",
          "bg_color" : "",
          "url_link" : null
        }, {
          "banner_nm" : "로맨틱 데이즈 홀터넥 슬림핏 레이스원피스",
          "img_url" : "http://image.lotte.com/goods/40/77/17/03/4/403177740_1_280.jpg",
          "img_link" : "-",
          "goods_no" : 403177740,
          "sold_out" : false,
          "price" : "60250",
          "brnd_nm" : "베리프리티",
          "bg_color" : "",
          "url_link" : null
        }, {
          "banner_nm" : "리얼끈슬리브리스",
          "img_url" : "http://image.lotte.com/goods/68/41/73/05/4/405734168_1_280.jpg",
          "img_link" : "-",
          "goods_no" : 405734168,
          "sold_out" : false,
          "price" : "17160",
          "brnd_nm" : "립합(LIPHOP)",
          "bg_color" : "",
          "url_link" : null
        }, {
          "banner_nm" : "시스루어필블랑",
          "img_url" : "http://image.lotte.com/goods/15/40/73/05/4/405734015_1_280.jpg",
          "img_link" : "-",
          "goods_no" : 405734015,
          "sold_out" : false,
          "price" : "11310",
          "brnd_nm" : "립합(LIPHOP)",
          "bg_color" : "",
          "url_link" : null
        }, {
          "banner_nm" : "블랙&골드 미니원피스",
          "img_url" : "http://image.lotte.com/goods/22/48/96/01/4/401964822_1_280.jpg",
          "img_link" : "-",
          "goods_no" : 401964822,
          "sold_out" : false,
          "price" : "53000",
          "brnd_nm" : "줄라이이십사",
          "bg_color" : "",
          "url_link" : null
        }, {
          "banner_nm" : "섹시백스트링",
          "img_url" : "http://image.lotte.com/goods/08/39/12/58/3/358123908_1_280.jpg",
          "img_link" : "-",
          "goods_no" : 358123908,
          "sold_out" : false,
          "price" : "53000",
          "brnd_nm" : "줄라이이십사",
          "bg_color" : "",
          "url_link" : null
        }, {
          "banner_nm" : "올비 원피스",
          "img_url" : "http://image.lotte.com/goods/54/63/19/71/3/371196354_1_280.jpg",
          "img_link" : "-",
          "goods_no" : 371196354,
          "sold_out" : false,
          "price" : "12650",
          "brnd_nm" : "츄샵",
          "bg_color" : "",
          "url_link" : null
        }, {
          "banner_nm" : "글래머러스홀터나시",
          "img_url" : "http://image.lotte.com/goods/60/56/39/05/4/405395660_1_280.jpg",
          "img_link" : "-",
          "goods_no" : 405395660,
          "sold_out" : false,
          "price" : "15600",
          "brnd_nm" : "립합(LIPHOP)",
          "bg_color" : "",
          "url_link" : null
        }, {
          "banner_nm" : "해바라기 오프숄더블라우스",
          "img_url" : "http://image.lotte.com/goods/09/63/09/97/3/397096309_1_280.jpg",
          "img_link" : "-",
          "goods_no" : 397096309,
          "sold_out" : false,
          "price" : "25500",
          "brnd_nm" : "임블리(imvely)",
          "bg_color" : "",
          "url_link" : null
        }, {
          "banner_nm" : "챠밍로즈원피스",
          "img_url" : "http://image.lotte.com/goods/07/27/46/91/3/391462707_1_280.jpg",
          "img_link" : "-",
          "goods_no" : 391462707,
          "sold_out" : false,
          "price" : "27840",
          "brnd_nm" : "쉬즈컴잉",
          "bg_color" : "",
          "url_link" : null
        }, {
          "banner_nm" : "스모크 뷔스티에",
          "img_url" : "http://image.lotte.com/goods/68/39/54/03/4/403543968_1_280.jpg",
          "img_link" : "-",
          "goods_no" : 403543968,
          "sold_out" : false,
          "price" : "17340",
          "brnd_nm" : "탐나나",
          "bg_color" : "",
          "url_link" : null
        }, {
          "banner_nm" : "자가드 크롭나시",
          "img_url" : "http://image.lotte.com/goods/18/28/13/97/3/397132818_1_280.jpg",
          "img_link" : "-",
          "goods_no" : 397132818,
          "sold_out" : false,
          "price" : "15360",
          "brnd_nm" : "탐나나",
          "bg_color" : "",
          "url_link" : null
        }, {
          "banner_nm" : "백크로스나시",
          "img_url" : "http://image.lotte.com/goods/77/79/37/05/4/405377977_1_280.jpg",
          "img_link" : "-",
          "goods_no" : 405377977,
          "sold_out" : false,
          "price" : "15210",
          "brnd_nm" : "립합(LIPHOP)",
          "bg_color" : "",
          "url_link" : null
        }, {
          "banner_nm" : "러블리 바캉스 롬퍼",
          "img_url" : "http://image.lotte.com/goods/19/51/96/01/4/401965119_1_280.jpg",
          "img_link" : "-",
          "goods_no" : 401965119,
          "sold_out" : false,
          "price" : "49000",
          "brnd_nm" : "줄라이이십사",
          "bg_color" : "",
          "url_link" : null
        }, {
          "banner_nm" : "스윙 원피스n가디건SET",
          "img_url" : "http://image.lotte.com/goods/83/57/34/65/3/365345783_1_280.jpg",
          "img_link" : "-",
          "goods_no" : 365345783,
          "sold_out" : false,
          "price" : "19930",
          "brnd_nm" : "츄샵",
          "bg_color" : "",
          "url_link" : null
        }, {
          "banner_nm" : "핑크디바원피스",
          "img_url" : "http://image.lotte.com/goods/66/76/12/79/3/379127666_1_280.jpg",
          "img_link" : "-",
          "goods_no" : 379127666,
          "sold_out" : false,
          "price" : "18420",
          "brnd_nm" : "톰앤래빗",
          "bg_color" : "",
          "url_link" : null
        }, {
          "banner_nm" : "미싱유 티셔츠",
          "img_url" : "http://image.lotte.com/goods/56/11/37/88/3/388371156_1_280.jpg",
          "img_link" : "-",
          "goods_no" : 388371156,
          "sold_out" : false,
          "price" : "9010",
          "brnd_nm" : "츄샵",
          "bg_color" : "",
          "url_link" : null
        }, {
          "banner_nm" : "S라인캡원피스",
          "img_url" : "http://image.lotte.com/goods/19/26/29/86/3/386292619_1_280.jpg",
          "img_link" : "-",
          "goods_no" : 386292619,
          "sold_out" : false,
          "price" : "31840",
          "brnd_nm" : "톰앤래빗",
          "bg_color" : "",
          "url_link" : null
        }, {
          "banner_nm" : "프릴캉캉블라우스",
          "img_url" : "http://image.lotte.com/goods/78/59/05/97/3/397055978_1_280.jpg",
          "img_link" : "-",
          "goods_no" : 397055978,
          "sold_out" : false,
          "price" : "18420",
          "brnd_nm" : "톰앤래빗",
          "bg_color" : "",
          "url_link" : null
        } ],
        "total_count" : 19
      },
      "hash_list" : [ ]
    },
    "brand_shop_list" : {
      "title" : "BRAND SHOP",
      "sub_title" : "쇼퍼들의 성지!!<br>잘나가는 언니들이 추천할게!",
      "banner_list" : {
        "items" : [ {
          "banner_nm" : "",
          "img_url" : "http://image.lotte.com/upload/display/corner/5550415_55355_0_30_13010132_1.jpg",
          "img_link" : "",
          "goods_no" : 0,
          "sold_out" : false,
          "price" : null,
          "brnd_nm" : null,
          "bg_color" : "",
          "url_link" : "/planshop/viewPlanShopDetail.lotte?spdp_no=5361250"
        }, {
          "banner_nm" : "",
          "img_url" : "http://image.lotte.com/upload/display/corner/5550415_55355_0_30_13010132_16.jpg",
          "img_link" : "",
          "goods_no" : 0,
          "sold_out" : false,
          "price" : null,
          "brnd_nm" : null,
          "bg_color" : "",
          "url_link" : "/planshop/viewPlanShopDetail.lotte?spdp_no=5365060"
        }, {
          "banner_nm" : "",
          "img_url" : "http://image.lotte.com/upload/display/corner/5550415_55355_0_30_13010132_9.jpg",
          "img_link" : "",
          "goods_no" : 0,
          "sold_out" : false,
          "price" : null,
          "brnd_nm" : null,
          "bg_color" : "",
          "url_link" : "/planshop/viewPlanShopDetail.lotte?spdp_no=5386876"
        }, {
          "banner_nm" : "281121",
          "img_url" : "http://image.lotte.com/upload/display/corner/5550415_55355_0_30_13010132_30.jpg",
          "img_link" : "281121",
          "goods_no" : 0,
          "sold_out" : false,
          "price" : null,
          "brnd_nm" : null,
          "bg_color" : "",
          "url_link" : "/planshop/viewPlanShopDetail.lotte?spdp_no=5413584"
        }, {
          "banner_nm" : "118808",
          "img_url" : "http://image.lotte.com/upload/display/corner/5550415_55355_0_30_13010132_10.jpg",
          "img_link" : "118808",
          "goods_no" : 0,
          "sold_out" : false,
          "price" : null,
          "brnd_nm" : null,
          "bg_color" : "",
          "url_link" : "/display/viewDispShop.lotte?disp_no=5526939"
        }, {
          "banner_nm" : "",
          "img_url" : "http://image.lotte.com/upload/display/corner/5550415_55355_0_30_13010132_14.jpg",
          "img_link" : "",
          "goods_no" : 0,
          "sold_out" : false,
          "price" : null,
          "brnd_nm" : null,
          "bg_color" : "",
          "url_link" : "/planshop/viewPlanShopDetail.lotte?spdp_no=5398208"
        }, {
          "banner_nm" : "",
          "img_url" : "http://image.lotte.com/upload/display/corner/5550415_55355_0_30_13010132_15.jpg",
          "img_link" : "",
          "goods_no" : 0,
          "sold_out" : false,
          "price" : null,
          "brnd_nm" : null,
          "bg_color" : "",
          "url_link" : "/planshop/viewPlanShopDetail.lotte?spdp_no=5398209"
        }, {
          "banner_nm" : "",
          "img_url" : "http://image.lotte.com/upload/display/corner/5550415_55355_0_30_13010132_2.jpg",
          "img_link" : "",
          "goods_no" : 0,
          "sold_out" : false,
          "price" : null,
          "brnd_nm" : null,
          "bg_color" : "",
          "url_link" : "/planshop/viewPlanShopDetail.lotte?spdp_no=5399810"
        }, {
          "banner_nm" : "",
          "img_url" : "http://image.lotte.com/upload/display/corner/5550415_55355_0_30_13010132_21.jpg",
          "img_link" : "",
          "goods_no" : 0,
          "sold_out" : false,
          "price" : null,
          "brnd_nm" : null,
          "bg_color" : "",
          "url_link" : "/planshop/viewPlanShopDetail.lotte?spdp_no=5398212"
        }, {
          "banner_nm" : "",
          "img_url" : "http://image.lotte.com/upload/display/corner/5550415_55355_0_30_13010132_3.jpg",
          "img_link" : "",
          "goods_no" : 0,
          "sold_out" : false,
          "price" : null,
          "brnd_nm" : null,
          "bg_color" : "",
          "url_link" : "/planshop/viewPlanShopDetail.lotte?spdp_no=5395819"
        }, {
          "banner_nm" : "",
          "img_url" : "http://image.lotte.com/upload/display/corner/5550415_55355_0_30_13010132_4.jpg",
          "img_link" : "",
          "goods_no" : 0,
          "sold_out" : false,
          "price" : null,
          "brnd_nm" : null,
          "bg_color" : "",
          "url_link" : "/planshop/viewPlanShopDetail.lotte?spdp_no=5379847"
        }, {
          "banner_nm" : "318810",
          "img_url" : "http://image.lotte.com/upload/display/corner/5550415_55355_0_30_13010132_27.jpg",
          "img_link" : "318810",
          "goods_no" : 0,
          "sold_out" : false,
          "price" : null,
          "brnd_nm" : null,
          "bg_color" : "",
          "url_link" : "/display/viewDispShop.lotte?disp_no=5543719"
        }, {
          "banner_nm" : "",
          "img_url" : "http://image.lotte.com/upload/display/corner/5550415_55355_0_30_13010132_26.jpg",
          "img_link" : "",
          "goods_no" : 0,
          "sold_out" : false,
          "price" : null,
          "brnd_nm" : null,
          "bg_color" : "",
          "url_link" : "/planshop/viewPlanShopDetail.lotte?spdp_no=5396966"
        }, {
          "banner_nm" : "281495",
          "img_url" : "http://image.lotte.com/upload/display/corner/5550415_55355_0_30_13010132_24.jpg",
          "img_link" : "281495",
          "goods_no" : 0,
          "sold_out" : false,
          "price" : null,
          "brnd_nm" : null,
          "bg_color" : "",
          "url_link" : "/display/viewDispShop.lotte?disp_no=5465699"
        }, {
          "banner_nm" : "",
          "img_url" : "http://image.lotte.com/upload/display/corner/5550415_55355_0_30_13010132_23.jpg",
          "img_link" : "",
          "goods_no" : 0,
          "sold_out" : false,
          "price" : null,
          "brnd_nm" : null,
          "bg_color" : "",
          "url_link" : "/planshop/viewPlanShopDetail.lotte?spdp_no=5391283"
        }, {
          "banner_nm" : "315056",
          "img_url" : "http://image.lotte.com/upload/display/corner/5550415_55355_0_30_13010132_22.jpg",
          "img_link" : "315056",
          "goods_no" : 0,
          "sold_out" : false,
          "price" : null,
          "brnd_nm" : null,
          "bg_color" : "",
          "url_link" : "/display/viewDispShop.lotte?disp_no=5547275"
        }, {
          "banner_nm" : "",
          "img_url" : "http://image.lotte.com/upload/display/corner/5550415_55355_0_30_13010132_18.jpg",
          "img_link" : "",
          "goods_no" : 0,
          "sold_out" : false,
          "price" : null,
          "brnd_nm" : null,
          "bg_color" : "",
          "url_link" : "/planshop/viewPlanShopDetail.lotte?spdp_no=5379922"
        }, {
          "banner_nm" : "309648",
          "img_url" : "http://image.lotte.com/upload/display/corner/5550415_55355_0_30_13010132_17.jpg",
          "img_link" : "309648",
          "goods_no" : 0,
          "sold_out" : false,
          "price" : null,
          "brnd_nm" : null,
          "bg_color" : "",
          "url_link" : "/display/viewDispShop.lotte?disp_no=5539295"
        }, {
          "banner_nm" : "",
          "img_url" : "http://image.lotte.com/upload/display/corner/5550415_55355_0_30_13010132_20.jpg",
          "img_link" : "",
          "goods_no" : 0,
          "sold_out" : false,
          "price" : null,
          "brnd_nm" : null,
          "bg_color" : "",
          "url_link" : "/planshop/viewPlanShopDetail.lotte?spdp_no=5380843"
        }, {
          "banner_nm" : "332941",
          "img_url" : "http://image.lotte.com/upload/display/corner/5550415_55355_0_30_13010132_25.jpg",
          "img_link" : "332941",
          "goods_no" : 0,
          "sold_out" : false,
          "price" : null,
          "brnd_nm" : null,
          "bg_color" : "",
          "url_link" : "/display/viewDispShop.lotte?disp_no=5561963"
        }, {
          "banner_nm" : "314415",
          "img_url" : "http://image.lotte.com/upload/display/corner/5550415_55355_0_30_13010132_28.jpg",
          "img_link" : "314415",
          "goods_no" : 0,
          "sold_out" : false,
          "price" : null,
          "brnd_nm" : null,
          "bg_color" : "",
          "url_link" : "/display/viewDispShop.lotte?disp_no=5543719"
        }, {
          "banner_nm" : "32741",
          "img_url" : "http://image.lotte.com/upload/display/corner/5550415_55355_0_30_13010132_5.jpg",
          "img_link" : "32741",
          "goods_no" : 0,
          "sold_out" : false,
          "price" : null,
          "brnd_nm" : null,
          "bg_color" : "",
          "url_link" : "/display/viewDispShop.lotte?disp_no=5463068"
        }, {
          "banner_nm" : "304204",
          "img_url" : "http://image.lotte.com/upload/display/corner/5550415_55355_0_30_13010132_35.jpg",
          "img_link" : "304204",
          "goods_no" : 0,
          "sold_out" : false,
          "price" : null,
          "brnd_nm" : null,
          "bg_color" : "",
          "url_link" : "/display/viewDispShop.lotte?disp_no=5532147"
        }, {
          "banner_nm" : "334740",
          "img_url" : "http://image.lotte.com/upload/display/corner/5550415_55355_0_30_13010132_34.jpg",
          "img_link" : "334740",
          "goods_no" : 0,
          "sold_out" : false,
          "price" : null,
          "brnd_nm" : null,
          "bg_color" : "",
          "url_link" : "/display/viewDispShop.lotte?disp_no=5563144"
        } ],
        "total_count" : 24
      },
      "hash_list" : [ ]
    },
    "cate_list" : {
      "items" : [ {
        "disp_nm" : "TOP",
        "disp_grp_no" : null,
        "disp_no" : "5550440",
        "img_url" : "",
        "link_url" : ""
      }, {
        "disp_nm" : "KNIT",
        "disp_grp_no" : null,
        "disp_no" : "5550441",
        "img_url" : "",
        "link_url" : ""
      }, {
        "disp_nm" : "DRESS",
        "disp_grp_no" : null,
        "disp_no" : "5550442",
        "img_url" : "",
        "link_url" : ""
      }, {
        "disp_nm" : "BOTTOM",
        "disp_grp_no" : null,
        "disp_no" : "5550443",
        "img_url" : "",
        "link_url" : ""
      }, {
        "disp_nm" : "OUTER",
        "disp_grp_no" : null,
        "disp_no" : "5550444",
        "img_url" : "",
        "link_url" : ""
      }, {
        "disp_nm" : "TRAINING",
        "disp_grp_no" : null,
        "disp_no" : "5550445",
        "img_url" : "",
        "link_url" : ""
      }, {
        "disp_nm" : "ACC",
        "disp_grp_no" : null,
        "disp_no" : "5550446",
        "img_url" : "",
        "link_url" : ""
      }, {
        "disp_nm" : "SEASON",
        "disp_grp_no" : null,
        "disp_no" : "5550447",
        "img_url" : "",
        "link_url" : ""
      }, {
        "disp_nm" : "ITEM",
        "disp_grp_no" : null,
        "disp_no" : "5551998",
        "img_url" : "",
        "link_url" : ""
      } ],
      "total_count" : 9
    },
    "top_banner_list" : null,
    "beauty_list" : {
      "title" : "곰손도 금손되는 비법♥",
      "sub_title" : "LOHB\u0027S 브러쉬 기획전",
      "banner_list_1" : {
        "items" : [ {
          "banner_nm" : "브.알.못 모여라",
          "img_url" : "http://image.lotte.com/upload/display/corner/5550415_58355_0_30_13010441_7.jpg",
          "img_link" : "/planshop/viewPlanShopDetail.lotte?spdp_no=5403740",
          "goods_no" : 0,
          "sold_out" : false,
          "price" : null,
          "brnd_nm" : null,
          "bg_color" : null,
          "url_link" : null
        } ],
        "total_count" : 1
      },
      "banner_list_2" : {
        "items" : [ {
          "banner_nm" : "탄력밀착",
          "img_url" : "http://image.lotte.com/goods/23/98/25/23/3/323259823_1_280.jpg",
          "img_link" : null,
          "goods_no" : 323259823,
          "sold_out" : false,
          "price" : null,
          "brnd_nm" : null,
          "bg_color" : null,
          "url_link" : null
        }, {
          "banner_nm" : "블러셔★",
          "img_url" : "http://image.lotte.com/goods/45/61/14/23/3/323146145_1_280.jpg",
          "img_link" : null,
          "goods_no" : 323146145,
          "sold_out" : false,
          "price" : null,
          "brnd_nm" : null,
          "bg_color" : null,
          "url_link" : null
        }, {
          "banner_nm" : "윤기창조",
          "img_url" : "http://image.lotte.com/goods/35/54/14/23/3/323145435_1_280.jpg",
          "img_link" : null,
          "goods_no" : 323145435,
          "sold_out" : false,
          "price" : null,
          "brnd_nm" : null,
          "bg_color" : null,
          "url_link" : null
        }, {
          "banner_nm" : "이걸로끝",
          "img_url" : "http://image.lotte.com/goods/04/48/14/23/3/323144804_1_280.jpg",
          "img_link" : null,
          "goods_no" : 323144804,
          "sold_out" : false,
          "price" : null,
          "brnd_nm" : null,
          "bg_color" : null,
          "url_link" : null
        } ],
        "total_count" : 4
      },
      "hash_list" : {
        "items" : [ {
          "hash_nm" : "1+1 마스크팩",
          "link_url" : "/planshop/viewPlanShopDetail.lotte?spdp_no=5403750"
        }, {
          "hash_nm" : "가성비갑 클렌징",
          "link_url" : "/planshop/viewPlanShopDetail.lotte?spdp_no=5403755"
        } ]
      }
    },
    "mov_plan" : null,
    "img_banner" : {
      "img_random" : false,
      "swip_banner" : null
    }
  }
}
