{
  "kShop" : {
    "logo" : {
      "alt":"로고",
      "imgUrl":"http://image.lotte.com/lotte/mo2017/category/specMallLogo_specialfood.png",
      "dispNo":"5558814"
    },
    "event": {
      "alt":"이벤트 배너",
      "imgUrl":"http://image.lotte.com/lotte/mo2017/category/spec_mall_new_banner.png ",
      "linkUrl":"http://m.lotte.com/product/m/product_list.do?curDispNo=5426870&c=mlotte&udid=&schema=&v=&cn=192426&cdn="
    },
    "banners" : {
      "items" : [ {
        "alt" : "크리스마스",
        "imgUrl" : "http://image.lotte.com/upload/display/corner/5558814_42956_47913_30_13008070_63_20171214143749.jpg",
        "linkUrl" : "http://m.lotte.com/mall/spec_mall_sub.do?dispNo=5558814&cate1=5572579&cate2=5583508&c=mlotte&cdn=&cn=&schema=&udid=&v="
      }, {
        "alt" : "고기의 맛",
        "imgUrl" : "http://image.lotte.com/upload/display/corner/5558814_42956_47913_30_13008070_61_20171205144035.jpg",
        "linkUrl" : "http://m.lotte.com/mall/spec_mall_sub.do?dispNo=5558814&cate1=5558816&cate2=5596398&c=mlotte&cdn=&cn=&schema=&udid=&v="
      }, {
        "alt" : "나물투데이_MO",
        "imgUrl" : "http://image.lotte.com/upload/display/corner/5558814_42956_47913_30_13008070_49.jpg",
        "linkUrl" : "http://m.lotte.com/mall/spec_mall_sub.do?dispNo=5558814&cate1=5570357&cate2=5593004"
      }, {
        "alt" : "수산_MO",
        "imgUrl" : "http://image.lotte.com/upload/display/corner/5558814_42956_47913_30_13008070_60.jpg",
        "linkUrl" : "http://m.lotte.com/mall/spec_mall_sub.do?dispNo=5558814&cate1=5558815&cate2=5573176&c=mlotte&cdn=&cn=&schema=&udid=&v="
      }, {
        "alt" : "건강한맛_MO",
        "imgUrl" : "http://image.lotte.com/upload/display/corner/5558814_42956_47913_30_13008070_62_20171206091754.jpg",
        "linkUrl" : "http://m.lotte.com/mall/spec_mall_sub.do?dispNo=5558814&cate1=5590198&cate2=5590203&c=mlotte&cdn=&cn=&schema=&udid=&v="
      }, {
        "alt" : "산지의맛 _MO",
        "imgUrl" : "http://image.lotte.com/upload/display/corner/5558814_42956_47913_30_13008070_57.jpg",
        "linkUrl" : "http://m.lotte.com/mall/spec_mall_sub.do?dispNo=5558814&cate1=5558815&cate2=5573174&c=mlotte&cdn=&cn=&schema=&udid=&v="
      }, {
        "alt" : "채소_MO",
        "imgUrl" : "http://image.lotte.com/upload/display/corner/5558814_42956_47913_30_13008070_56.jpg",
        "linkUrl" : "http://m.lotte.com/mall/spec_mall_sub.do?dispNo=5558814&cate1=5558815&cate2=5573175&c=mlotte&cdn=&cn=&schema=&udid=&v="
      } ],
      "total_count" : 6
    },
    "prdList" : {
      "items" : [ {
        "ctgName" : "가을이에요! 제철 식품이 땡겨요!",
        "product" : [ {
          "goods_no" : 303538030,
          "goods_nm" : "2017 청도반시 특품 10kg 90과~99과",
          "brnd_nm" : "롯데식품관",
          "curDispNo" : "",
          "flag" : "",
          "is_sale_promotion" : false,
          "img_url" : "http://image.lotte.com/goods/30/80/53/03/3/303538030_1_280.jpg",
          "img_url_550" : "http://image.lotte.com/goods/30/80/53/03/3/303538030_1_550.jpg",
          "isCrsPickYn" : false,
          "is_dept" : false,
          "isDeptPickYn" : false,
          "isDlvToday" : false,
          "isDlvQuick" : false,
          "is_himart" : false,
          "smartpick_yn" : "N",
          "is_tvhome" : false,
          "is_youngplz" : false,
          "outlnk" : null,
          "outlnkMall" : null,
          "original_price" : 0,
          "discounted_price" : 13500,
          "sale_rate" : 0,
          "is_sold_out" : false,
          "has_coupon" : false,
          "has_wish" : false,
          "review_count" : 17,
          "bought_sum" : 0,
          "find_age" : null,
          "find_gender" : null,
          "md_tip" : null,
          "promotion_text" : null,
          "isdlex_free" : true,
          "sold_out_cd_yn" : null,
          "limit_age_yn" : "N",
          "link_url" : null,
          "hash_list" : [ ],
          "nint_card_flag" : "",
          "avg_gdas_stfd_val" : "4.8",
          "gdasInfo" : null,
          "save_lpoint" : 0,
          "upr_md_gsgr_no" : 0,
          "mpic_info" : null 
        }, {
          "goods_no" : 365368266,
          "goods_nm" : "껍질째먹는 햇! 빨간세척사과 3kg(실중량/14-20내)",
          "brnd_nm" : "롯데식품관",
          "curDispNo" : "",
          "flag" : "",
          "is_sale_promotion" : false,
          "img_url" : "http://image.lotte.com/goods/66/82/36/65/3/365368266_2_280.jpg",
          "img_url_550" : "http://image.lotte.com/goods/66/82/36/65/3/365368266_2_550.jpg",
          "isCrsPickYn" : false,
          "is_dept" : false,
          "isDeptPickYn" : false,
          "isDlvToday" : false,
          "isDlvQuick" : false,
          "is_himart" : false,
          "smartpick_yn" : "N",
          "is_tvhome" : false,
          "is_youngplz" : false,
          "outlnk" : null,
          "outlnkMall" : null,
          "original_price" : 13500,
          "discounted_price" : 12900,
          "sale_rate" : 0,
          "is_sold_out" : false,
          "has_coupon" : false,
          "has_wish" : false,
          "review_count" : 77,
          "bought_sum" : 0,
          "find_age" : null,
          "find_gender" : null,
          "md_tip" : null,
          "promotion_text" : null,
          "isdlex_free" : false,
          "sold_out_cd_yn" : null,
          "limit_age_yn" : "N",
          "link_url" : null,
          "hash_list" : [ ],
          "nint_card_flag" : "",
          "avg_gdas_stfd_val" : "4.7",
          "gdasInfo" : null,
          "save_lpoint" : 0,
          "upr_md_gsgr_no" : 0,
          "mpic_info" : null
        } ]
      }, {
        "ctgName" : "싱싱한 바다의 향기를 느껴보아요!",
        "product" : [ {
          "goods_no" : 385558572,
          "goods_nm" : "부드럽고 달달한 총알 오징어 1kg (5마리 내외)",
          "brnd_nm" : "롯데식품관",
          "curDispNo" : "",
          "flag" : "",
          "is_sale_promotion" : false,
          "img_url" : "http://image.lotte.com/goods/72/85/55/85/3/385558572_1_280.jpg",
          "img_url_550" : "http://image.lotte.com/goods/72/85/55/85/3/385558572_1_550.jpg",
          "isCrsPickYn" : false,
          "is_dept" : false,
          "isDeptPickYn" : false,
          "isDlvToday" : false,
          "isDlvQuick" : false,
          "is_himart" : false,
          "smartpick_yn" : "N",
          "is_tvhome" : false,
          "is_youngplz" : false,
          "outlnk" : null,
          "outlnkMall" : null,
          "original_price" : 0,
          "discounted_price" : 15900,
          "sale_rate" : 0,
          "is_sold_out" : false,
          "has_coupon" : false,
          "has_wish" : false,
          "review_count" : 13,
          "bought_sum" : 0,
          "find_age" : null,
          "find_gender" : null,
          "md_tip" : null,
          "promotion_text" : null,
          "isdlex_free" : false,
          "sold_out_cd_yn" : null,
          "limit_age_yn" : "N",
          "link_url" : null,
          "hash_list" : [ ],
          "nint_card_flag" : "",
          "avg_gdas_stfd_val" : "4.3",
          "gdasInfo" : null,
          "save_lpoint" : 0,
          "upr_md_gsgr_no" : 0,
          "mpic_info" : null
        }, {
          "goods_no" : 367927684,
          "goods_nm" : "[농부마음] 산지직송 완도 활전복 1kg(꼬마)",
          "brnd_nm" : "롯데식품관",
          "curDispNo" : "",
          "flag" : "",
          "is_sale_promotion" : false,
          "img_url" : "http://image.lotte.com/goods/84/76/92/67/3/367927684_1_280.jpg",
          "img_url_550" : "http://image.lotte.com/goods/84/76/92/67/3/367927684_1_550.jpg",
          "isCrsPickYn" : false,
          "is_dept" : false,
          "isDeptPickYn" : false,
          "isDlvToday" : false,
          "isDlvQuick" : false,
          "is_himart" : false,
          "smartpick_yn" : "N",
          "is_tvhome" : false,
          "is_youngplz" : false,
          "outlnk" : null,
          "outlnkMall" : null,
          "original_price" : 0,
          "discounted_price" : 25900,
          "sale_rate" : 0,
          "is_sold_out" : false,
          "has_coupon" : false,
          "has_wish" : false,
          "review_count" : 4,
          "bought_sum" : 0,
          "find_age" : null,
          "find_gender" : null,
          "md_tip" : null,
          "promotion_text" : null,
          "isdlex_free" : false,
          "sold_out_cd_yn" : null,
          "limit_age_yn" : "N",
          "link_url" : null,
          "hash_list" : [ ],
          "nint_card_flag" : "",
          "avg_gdas_stfd_val" : "5.0",
          "gdasInfo" : null,
          "save_lpoint" : 0,
          "upr_md_gsgr_no" : 0,
          "mpic_info" : null
        } ]
      }, {
        "ctgName" : "산지를 바로 느껴봐요!",
        "product" : [ {
          "goods_no" : 410904198,
          "goods_nm" : "해남 김형식 생산자의 밤고구마 5kg (특상)",
          "brnd_nm" : "푸르젠",
          "curDispNo" : "",
          "flag" : "",
          "is_sale_promotion" : false,
          "img_url" : "http://image.lotte.com/goods/98/41/90/10/4/410904198_2_280.jpg",
          "img_url_550" : "http://image.lotte.com/goods/98/41/90/10/4/410904198_2_550.jpg",
          "isCrsPickYn" : false,
          "is_dept" : false,
          "isDeptPickYn" : false,
          "isDlvToday" : false,
          "isDlvQuick" : false,
          "is_himart" : false,
          "smartpick_yn" : "N",
          "is_tvhome" : false,
          "is_youngplz" : false,
          "outlnk" : null,
          "outlnkMall" : null,
          "original_price" : 0,
          "discounted_price" : 14900,
          "sale_rate" : 0,
          "is_sold_out" : false,
          "has_coupon" : false,
          "has_wish" : false,
          "review_count" : 16,
          "bought_sum" : 0,
          "find_age" : null,
          "find_gender" : null,
          "md_tip" : null,
          "promotion_text" : null,
          "isdlex_free" : false,
          "sold_out_cd_yn" : null,
          "limit_age_yn" : "N",
          "link_url" : null,
          "hash_list" : [ ],
          "nint_card_flag" : "",
          "avg_gdas_stfd_val" : "4.9",
          "gdasInfo" : null,
          "save_lpoint" : 0,
          "upr_md_gsgr_no" : 0,
          "mpic_info" : null
        }, {
          "goods_no" : 441789576,
          "goods_nm" : "해남 김형식 생산자의 꿀고구마 10kg (특상)",
          "brnd_nm" : "푸르젠",
          "curDispNo" : "",
          "flag" : "",
          "is_sale_promotion" : false,
          "img_url" : "http://image.lotte.com/goods/76/95/78/41/4/441789576_1_280.jpg",
          "img_url_550" : "http://image.lotte.com/goods/76/95/78/41/4/441789576_1_550.jpg",
          "isCrsPickYn" : false,
          "is_dept" : false,
          "isDeptPickYn" : false,
          "isDlvToday" : false,
          "isDlvQuick" : false,
          "is_himart" : false,
          "smartpick_yn" : "N",
          "is_tvhome" : false,
          "is_youngplz" : false,
          "outlnk" : null,
          "outlnkMall" : null,
          "original_price" : 0,
          "discounted_price" : 26900,
          "sale_rate" : 0,
          "is_sold_out" : false,
          "has_coupon" : false,
          "has_wish" : false,
          "review_count" : 2,
          "bought_sum" : 0,
          "find_age" : null,
          "find_gender" : null,
          "md_tip" : null,
          "promotion_text" : null,
          "isdlex_free" : false,
          "sold_out_cd_yn" : null,
          "limit_age_yn" : "N",
          "link_url" : null,
          "hash_list" : [ ],
          "nint_card_flag" : "",
          "avg_gdas_stfd_val" : "5.0",
          "gdasInfo" : null,
          "save_lpoint" : 0,
          "upr_md_gsgr_no" : 0,
          "mpic_info" : null
        } ]
      }, {
        "ctgName" : "나를 위해 클렌즈하자!",
        "product" : [ {
          "goods_no" : 315896266,
          "goods_nm" : "박지윤의 욕망스무디 5day 프로그램(20팩)/건강 클렌즈",
          "brnd_nm" : "욕망스무디",
          "curDispNo" : "",
          "flag" : "",
          "is_sale_promotion" : false,
          "img_url" : "http://image.lotte.com/goods/66/62/89/15/3/315896266_2_280.jpg",
          "img_url_550" : "http://image.lotte.com/goods/66/62/89/15/3/315896266_2_550.jpg",
          "isCrsPickYn" : false,
          "is_dept" : false,
          "isDeptPickYn" : false,
          "isDlvToday" : false,
          "isDlvQuick" : false,
          "is_himart" : false,
          "smartpick_yn" : "N",
          "is_tvhome" : false,
          "is_youngplz" : false,
          "outlnk" : null,
          "outlnkMall" : null,
          "original_price" : 0,
          "discounted_price" : 79900,
          "sale_rate" : 0,
          "is_sold_out" : false,
          "has_coupon" : false,
          "has_wish" : false,
          "review_count" : 309,
          "bought_sum" : 0,
          "find_age" : null,
          "find_gender" : null,
          "md_tip" : null,
          "promotion_text" : null,
          "isdlex_free" : false,
          "sold_out_cd_yn" : null,
          "limit_age_yn" : "N",
          "link_url" : null,
          "hash_list" : [ ],
          "nint_card_flag" : "무이자10",
          "avg_gdas_stfd_val" : "4.8",
          "gdasInfo" : null,
          "save_lpoint" : 0,
          "upr_md_gsgr_no" : 0,
          "mpic_info" : null
        }, {
          "goods_no" : 396624741,
          "goods_nm" : "저스트주스 클렌즈 미니(250mlx18)무화과햄프",
          "brnd_nm" : "올가니카",
          "curDispNo" : "",
          "flag" : "",
          "is_sale_promotion" : false,
          "img_url" : "http://image.lotte.com/goods/41/47/62/96/3/396624741_2_280.jpg",
          "img_url_550" : "http://image.lotte.com/goods/41/47/62/96/3/396624741_2_550.jpg",
          "isCrsPickYn" : false,
          "is_dept" : false,
          "isDeptPickYn" : false,
          "isDlvToday" : false,
          "isDlvQuick" : false,
          "is_himart" : false,
          "smartpick_yn" : "N",
          "is_tvhome" : false,
          "is_youngplz" : false,
          "outlnk" : null,
          "outlnkMall" : null,
          "original_price" : 72900,
          "discounted_price" : 66340,
          "sale_rate" : 0,
          "is_sold_out" : false,
          "has_coupon" : false,
          "has_wish" : false,
          "review_count" : 32,
          "bought_sum" : 0,
          "find_age" : null,
          "find_gender" : null,
          "md_tip" : null,
          "promotion_text" : null,
          "isdlex_free" : false,
          "sold_out_cd_yn" : null,
          "limit_age_yn" : "N",
          "link_url" : null,
          "hash_list" : [ ],
          "nint_card_flag" : "무이자10",
          "avg_gdas_stfd_val" : "4.9",
          "gdasInfo" : null,
          "save_lpoint" : 0,
          "upr_md_gsgr_no" : 0,
          "mpic_info" : null
        } ]
      }, {
        "ctgName" : "밤식빵도 해먹고 숟가락으로 파먹고!",
        "product" : [ {
          "goods_no" : 295184256,
          "goods_nm" : "[밤愛]국내산 충주 밤2kg(중)",
          "brnd_nm" : "롯데식품관",
          "curDispNo" : "",
          "flag" : "",
          "is_sale_promotion" : false,
          "img_url" : "http://image.lotte.com/goods/56/42/18/95/2/295184256_1_280.jpg",
          "img_url_550" : "http://image.lotte.com/goods/56/42/18/95/2/295184256_1_550.jpg",
          "isCrsPickYn" : false,
          "is_dept" : false,
          "isDeptPickYn" : false,
          "isDlvToday" : false,
          "isDlvQuick" : false,
          "is_himart" : false,
          "smartpick_yn" : "N",
          "is_tvhome" : false,
          "is_youngplz" : false,
          "outlnk" : null,
          "outlnkMall" : null,
          "original_price" : 0,
          "discounted_price" : 11900,
          "sale_rate" : 0,
          "is_sold_out" : false,
          "has_coupon" : false,
          "has_wish" : false,
          "review_count" : 5,
          "bought_sum" : 0,
          "find_age" : null,
          "find_gender" : null,
          "md_tip" : null,
          "promotion_text" : null,
          "isdlex_free" : false,
          "sold_out_cd_yn" : null,
          "limit_age_yn" : "N",
          "link_url" : null,
          "hash_list" : [ ],
          "nint_card_flag" : "",
          "avg_gdas_stfd_val" : "3.8",
          "gdasInfo" : null,
          "save_lpoint" : 0,
          "upr_md_gsgr_no" : 0,
          "mpic_info" : null
        }, {
          "goods_no" : 308903382,
          "goods_nm" : "구수하고 달콤한 약단밤 1kg",
          "brnd_nm" : "푸르젠",
          "curDispNo" : "",
          "flag" : "",
          "is_sale_promotion" : false,
          "img_url" : "http://image.lotte.com/goods/82/33/90/08/3/308903382_1_280.jpg",
          "img_url_550" : "http://image.lotte.com/goods/82/33/90/08/3/308903382_1_550.jpg",
          "isCrsPickYn" : false,
          "is_dept" : false,
          "isDeptPickYn" : false,
          "isDlvToday" : false,
          "isDlvQuick" : false,
          "is_himart" : false,
          "smartpick_yn" : "N",
          "is_tvhome" : false,
          "is_youngplz" : false,
          "outlnk" : null,
          "outlnkMall" : null,
          "original_price" : 0,
          "discounted_price" : 7900,
          "sale_rate" : 0,
          "is_sold_out" : false,
          "has_coupon" : false,
          "has_wish" : false,
          "review_count" : 139,
          "bought_sum" : 0,
          "find_age" : null,
          "find_gender" : null,
          "md_tip" : null,
          "promotion_text" : null,
          "isdlex_free" : false,
          "sold_out_cd_yn" : null,
          "limit_age_yn" : "N",
          "link_url" : null,
          "hash_list" : [ ],
          "nint_card_flag" : "",
          "avg_gdas_stfd_val" : "4.8",
          "gdasInfo" : null,
          "save_lpoint" : 0,
          "upr_md_gsgr_no" : 0,
          "mpic_info" : null
        } ]
      } ],
      "total_count" : 5
    },
    "prdList2" : {
      "items" : [ {
        "ctgName" : "첫 번째 세트 타이틀(test)",
        "product" : [ {
          "goods_no" : 393881084,
          "goods_nm" : "천안맛집 튀김소보로 호두과자 16개입",
          "brnd_nm" : "사그담",
          "curDispNo" : "",
          "flag" : "",
          "is_sale_promotion" : false,
          "img_url" : "http://image.lotte.com/goods/84/10/88/93/3/393881084_1_280.jpg",
          "img_url_550" : "http://image.lotte.com/goods/84/10/88/93/3/393881084_1_550.jpg",
          "isCrsPickYn" : false,
          "is_dept" : false,
          "isDeptPickYn" : false,
          "isDlvToday" : false,
          "isDlvQuick" : false,
          "is_himart" : false,
          "smartpick_yn" : "N",
          "is_tvhome" : false,
          "is_youngplz" : false,
          "outlnk" : null,
          "outlnkMall" : null,
          "original_price" : 0,
          "discounted_price" : 10000,
          "sale_rate" : 0,
          "is_sold_out" : false,
          "has_coupon" : false,
          "has_wish" : false,
          "review_count" : 3,
          "bought_sum" : 0,
          "find_age" : null,
          "find_gender" : null,
          "md_tip" : null,
          "promotion_text" : null,
          "isdlex_free" : false,
          "sold_out_cd_yn" : null,
          "limit_age_yn" : "N",
          "link_url" : null,
          "hash_list" : [ ],
          "nint_card_flag" : "",
          "avg_gdas_stfd_val" : "4.7",
          "gdasInfo" : null,
          "save_lpoint" : 0,
          "upr_md_gsgr_no" : 0,
          "mpic_info" : null
        }, {
          "goods_no" : 379502213,
          "goods_nm" : "생활의 달인 그! 도담떡집의 전문 이북식인절미★ 도담떡",
          "brnd_nm" : "식탁이있는삶",
          "curDispNo" : "",
          "flag" : "",
          "is_sale_promotion" : true,
          "img_url" : "http://image.lotte.com/goods/13/22/50/79/3/379502213_2_280.jpg",
          "img_url_550" : "http://image.lotte.com/goods/13/22/50/79/3/379502213_2_550.jpg",
          "isCrsPickYn" : false,
          "is_dept" : false,
          "isDeptPickYn" : false,
          "isDlvToday" : false,
          "isDlvQuick" : false,
          "is_himart" : false,
          "smartpick_yn" : "N",
          "is_tvhome" : false,
          "is_youngplz" : false,
          "outlnk" : null,
          "outlnkMall" : null,
          "original_price" : 20000,
          "discounted_price" : 18900,
          "sale_rate" : 0,
          "is_sold_out" : false,
          "has_coupon" : false,
          "has_wish" : false,
          "review_count" : 0,
          "bought_sum" : 0,
          "find_age" : null,
          "find_gender" : null,
          "md_tip" : null,
          "promotion_text" : null,
          "isdlex_free" : false,
          "sold_out_cd_yn" : null,
          "limit_age_yn" : "N",
          "link_url" : null,
          "hash_list" : [ ],
          "nint_card_flag" : "",
          "avg_gdas_stfd_val" : "0.0",
          "gdasInfo" : null,
          "save_lpoint" : 0,
          "upr_md_gsgr_no" : 0,
          "mpic_info" : null
        }, {
          "goods_no" : 358132196,
          "goods_nm" : "국산팥100% 아이스 단팥크림빵95g 8개",
          "brnd_nm" : "소적두",
          "curDispNo" : "",
          "flag" : "",
          "is_sale_promotion" : false,
          "img_url" : "http://image.lotte.com/goods/96/21/13/58/3/358132196_1_280.jpg",
          "img_url_550" : "http://image.lotte.com/goods/96/21/13/58/3/358132196_1_550.jpg",
          "isCrsPickYn" : false,
          "is_dept" : false,
          "isDeptPickYn" : false,
          "isDlvToday" : false,
          "isDlvQuick" : false,
          "is_himart" : false,
          "smartpick_yn" : "N",
          "is_tvhome" : false,
          "is_youngplz" : false,
          "outlnk" : null,
          "outlnkMall" : null,
          "original_price" : 24500,
          "discounted_price" : 20000,
          "sale_rate" : 0,
          "is_sold_out" : false,
          "has_coupon" : false,
          "has_wish" : false,
          "review_count" : 1,
          "bought_sum" : 0,
          "find_age" : null,
          "find_gender" : null,
          "md_tip" : null,
          "promotion_text" : null,
          "isdlex_free" : false,
          "sold_out_cd_yn" : null,
          "limit_age_yn" : "N",
          "link_url" : null,
          "hash_list" : [ ],
          "nint_card_flag" : "",
          "avg_gdas_stfd_val" : "1.0",
          "gdasInfo" : null,
          "save_lpoint" : 0,
          "upr_md_gsgr_no" : 0,
          "mpic_info" : null
        }, {
          "goods_no" : 346342645,
          "goods_nm" : "[무료배송] 블루베리 크림치즈+누텔라 크림치즈+베이글 1봉지(6개입)",
          "brnd_nm" : "모노치즈",
          "curDispNo" : "",
          "flag" : "",
          "is_sale_promotion" : false,
          "img_url" : "http://image.lotte.com/goods/45/26/34/46/3/346342645_5_280.jpg",
          "img_url_550" : "http://image.lotte.com/goods/45/26/34/46/3/346342645_5_550.jpg",
          "isCrsPickYn" : false,
          "is_dept" : false,
          "isDeptPickYn" : false,
          "isDlvToday" : false,
          "isDlvQuick" : false,
          "is_himart" : false,
          "smartpick_yn" : "N",
          "is_tvhome" : false,
          "is_youngplz" : false,
          "outlnk" : null,
          "outlnkMall" : null,
          "original_price" : 0,
          "discounted_price" : 17000,
          "sale_rate" : 0,
          "is_sold_out" : false,
          "has_coupon" : false,
          "has_wish" : false,
          "review_count" : 15,
          "bought_sum" : 0,
          "find_age" : null,
          "find_gender" : null,
          "md_tip" : null,
          "promotion_text" : null,
          "isdlex_free" : false,
          "sold_out_cd_yn" : null,
          "limit_age_yn" : "N",
          "link_url" : null,
          "hash_list" : [ ],
          "nint_card_flag" : "",
          "avg_gdas_stfd_val" : "5.0",
          "gdasInfo" : null,
          "save_lpoint" : 0,
          "upr_md_gsgr_no" : 0,
          "mpic_info" : null
        }, {
          "goods_no" : 319895610,
          "goods_nm" : "1+1 골라담기 숙대명물 이상용 유기농 롤케익",
          "brnd_nm" : "크레마롤",
          "curDispNo" : "",
          "flag" : "",
          "is_sale_promotion" : false,
          "img_url" : "http://image.lotte.com/goods/10/56/89/19/3/319895610_1_280.jpg",
          "img_url_550" : "http://image.lotte.com/goods/10/56/89/19/3/319895610_1_550.jpg",
          "isCrsPickYn" : false,
          "is_dept" : false,
          "isDeptPickYn" : false,
          "isDlvToday" : false,
          "isDlvQuick" : false,
          "is_himart" : false,
          "smartpick_yn" : "N",
          "is_tvhome" : false,
          "is_youngplz" : false,
          "outlnk" : null,
          "outlnkMall" : null,
          "original_price" : 34900,
          "discounted_price" : 33160,
          "sale_rate" : 0,
          "is_sold_out" : false,
          "has_coupon" : false,
          "has_wish" : false,
          "review_count" : 38,
          "bought_sum" : 0,
          "find_age" : null,
          "find_gender" : null,
          "md_tip" : null,
          "promotion_text" : null,
          "isdlex_free" : false,
          "sold_out_cd_yn" : null,
          "limit_age_yn" : "N",
          "link_url" : null,
          "hash_list" : [ ],
          "nint_card_flag" : "",
          "avg_gdas_stfd_val" : "4.2",
          "gdasInfo" : null,
          "save_lpoint" : 0,
          "upr_md_gsgr_no" : 0,
          "mpic_info" : null
        }, {
          "goods_no" : 256588932,
          "goods_nm" : "제주도 직송! 제주 오메기떡 4종 택1",
          "brnd_nm" : "롯데식품관",
          "curDispNo" : "",
          "flag" : "",
          "is_sale_promotion" : true,
          "img_url" : "http://image.lotte.com/goods/32/89/58/56/2/256588932_1_280.jpg",
          "img_url_550" : "http://image.lotte.com/goods/32/89/58/56/2/256588932_1_550.jpg",
          "isCrsPickYn" : false,
          "is_dept" : false,
          "isDeptPickYn" : false,
          "isDlvToday" : false,
          "isDlvQuick" : false,
          "is_himart" : false,
          "smartpick_yn" : "N",
          "is_tvhome" : false,
          "is_youngplz" : false,
          "outlnk" : null,
          "outlnkMall" : null,
          "original_price" : 33900,
          "discounted_price" : 20900,
          "sale_rate" : 0,
          "is_sold_out" : false,
          "has_coupon" : false,
          "has_wish" : false,
          "review_count" : 0,
          "bought_sum" : 0,
          "find_age" : null,
          "find_gender" : null,
          "md_tip" : null,
          "promotion_text" : null,
          "isdlex_free" : false,
          "sold_out_cd_yn" : null,
          "limit_age_yn" : "N",
          "link_url" : null,
          "hash_list" : [ ],
          "nint_card_flag" : "",
          "avg_gdas_stfd_val" : "0.0",
          "gdasInfo" : null,
          "save_lpoint" : 0,
          "upr_md_gsgr_no" : 0,
          "mpic_info" : null
        },  {
          "goods_no" : 396621791,
          "goods_nm" : "[경북 포항] 진짜 오징어가 들어간 오징어빵",
          "brnd_nm" : "사그담",
          "curDispNo" : "",
          "flag" : "",
          "is_sale_promotion" : false,
          "img_url" : "http://image.lotte.com/goods/91/17/62/96/3/396621791_1_280.jpg",
          "img_url_550" : "http://image.lotte.com/goods/91/17/62/96/3/396621791_1_550.jpg",
          "isCrsPickYn" : false,
          "is_dept" : false,
          "isDeptPickYn" : false,
          "isDlvToday" : false,
          "isDlvQuick" : false,
          "is_himart" : false,
          "smartpick_yn" : "N",
          "is_tvhome" : false,
          "is_youngplz" : false,
          "outlnk" : null,
          "outlnkMall" : null,
          "original_price" : 0,
          "discounted_price" : 12000,
          "sale_rate" : 0,
          "is_sold_out" : false,
          "has_coupon" : false,
          "has_wish" : false,
          "review_count" : 0,
          "bought_sum" : 0,
          "find_age" : null,
          "find_gender" : null,
          "md_tip" : null,
          "promotion_text" : null,
          "isdlex_free" : false,
          "sold_out_cd_yn" : null,
          "limit_age_yn" : "N",
          "link_url" : null,
          "hash_list" : [ ],
          "nint_card_flag" : "",
          "avg_gdas_stfd_val" : "0.0",
          "gdasInfo" : null,
          "save_lpoint" : 0,
          "upr_md_gsgr_no" : 0,
          "mpic_info" : null
        }, {
          "goods_no" : 393880992,
          "goods_nm" : "천안맛집 옛날호두과자 40개입",
          "brnd_nm" : "사그담",
          "curDispNo" : "",
          "flag" : "",
          "is_sale_promotion" : false,
          "img_url" : "http://image.lotte.com/goods/92/09/88/93/3/393880992_1_280.jpg",
          "img_url_550" : "http://image.lotte.com/goods/92/09/88/93/3/393880992_1_550.jpg",
          "isCrsPickYn" : false,
          "is_dept" : false,
          "isDeptPickYn" : false,
          "isDlvToday" : false,
          "isDlvQuick" : false,
          "is_himart" : false,
          "smartpick_yn" : "N",
          "is_tvhome" : false,
          "is_youngplz" : false,
          "outlnk" : null,
          "outlnkMall" : null,
          "original_price" : 0,
          "discounted_price" : 10000,
          "sale_rate" : 0,
          "is_sold_out" : false,
          "has_coupon" : false,
          "has_wish" : false,
          "review_count" : 0,
          "bought_sum" : 0,
          "find_age" : null,
          "find_gender" : null,
          "md_tip" : null,
          "promotion_text" : null,
          "isdlex_free" : false,
          "sold_out_cd_yn" : null,
          "limit_age_yn" : "N",
          "link_url" : null,
          "hash_list" : [ ],
          "nint_card_flag" : "",
          "avg_gdas_stfd_val" : "0.0",
          "gdasInfo" : null,
          "save_lpoint" : 0,
          "upr_md_gsgr_no" : 0,
          "mpic_info" : null
        } ]
      }, {
        "ctgName" : "두 번째 세트 타이틀(test)",
        "product" : [ {
          "goods_no" : 396621750,
          "goods_nm" : "[경북 포항] 진짜 문어가 들어간 문어빵",
          "brnd_nm" : "사그담",
          "curDispNo" : "",
          "flag" : "",
          "is_sale_promotion" : false,
          "img_url" : "http://image.lotte.com/goods/50/17/62/96/3/396621750_1_280.jpg",
          "img_url_550" : "http://image.lotte.com/goods/50/17/62/96/3/396621750_1_550.jpg",
          "isCrsPickYn" : false,
          "is_dept" : false,
          "isDeptPickYn" : false,
          "isDlvToday" : false,
          "isDlvQuick" : false,
          "is_himart" : false,
          "smartpick_yn" : "N",
          "is_tvhome" : false,
          "is_youngplz" : false,
          "outlnk" : null,
          "outlnkMall" : null,
          "original_price" : 0,
          "discounted_price" : 12000,
          "sale_rate" : 0,
          "is_sold_out" : false,
          "has_coupon" : false,
          "has_wish" : false,
          "review_count" : 0,
          "bought_sum" : 0,
          "find_age" : null,
          "find_gender" : null,
          "md_tip" : null,
          "promotion_text" : null,
          "isdlex_free" : false,
          "sold_out_cd_yn" : null,
          "limit_age_yn" : "N",
          "link_url" : null,
          "hash_list" : [ ],
          "nint_card_flag" : "",
          "avg_gdas_stfd_val" : "0.0",
          "gdasInfo" : null,
          "save_lpoint" : 0,
          "upr_md_gsgr_no" : 0,
          "mpic_info" : null
        }, {
          "goods_no" : 396621791,
          "goods_nm" : "[경북 포항] 진짜 오징어가 들어간 오징어빵",
          "brnd_nm" : "사그담",
          "curDispNo" : "",
          "flag" : "",
          "is_sale_promotion" : false,
          "img_url" : "http://image.lotte.com/goods/91/17/62/96/3/396621791_1_280.jpg",
          "img_url_550" : "http://image.lotte.com/goods/91/17/62/96/3/396621791_1_550.jpg",
          "isCrsPickYn" : false,
          "is_dept" : false,
          "isDeptPickYn" : false,
          "isDlvToday" : false,
          "isDlvQuick" : false,
          "is_himart" : false,
          "smartpick_yn" : "N",
          "is_tvhome" : false,
          "is_youngplz" : false,
          "outlnk" : null,
          "outlnkMall" : null,
          "original_price" : 0,
          "discounted_price" : 12000,
          "sale_rate" : 0,
          "is_sold_out" : false,
          "has_coupon" : false,
          "has_wish" : false,
          "review_count" : 0,
          "bought_sum" : 0,
          "find_age" : null,
          "find_gender" : null,
          "md_tip" : null,
          "promotion_text" : null,
          "isdlex_free" : false,
          "sold_out_cd_yn" : null,
          "limit_age_yn" : "N",
          "link_url" : null,
          "hash_list" : [ ],
          "nint_card_flag" : "",
          "avg_gdas_stfd_val" : "0.0",
          "gdasInfo" : null,
          "save_lpoint" : 0,
          "upr_md_gsgr_no" : 0,
          "mpic_info" : null
        }, {
          "goods_no" : 393880992,
          "goods_nm" : "천안맛집 옛날호두과자 40개입",
          "brnd_nm" : "사그담",
          "curDispNo" : "",
          "flag" : "",
          "is_sale_promotion" : false,
          "img_url" : "http://image.lotte.com/goods/92/09/88/93/3/393880992_1_280.jpg",
          "img_url_550" : "http://image.lotte.com/goods/92/09/88/93/3/393880992_1_550.jpg",
          "isCrsPickYn" : false,
          "is_dept" : false,
          "isDeptPickYn" : false,
          "isDlvToday" : false,
          "isDlvQuick" : false,
          "is_himart" : false,
          "smartpick_yn" : "N",
          "is_tvhome" : false,
          "is_youngplz" : false,
          "outlnk" : null,
          "outlnkMall" : null,
          "original_price" : 0,
          "discounted_price" : 10000,
          "sale_rate" : 0,
          "is_sold_out" : false,
          "has_coupon" : false,
          "has_wish" : false,
          "review_count" : 0,
          "bought_sum" : 0,
          "find_age" : null,
          "find_gender" : null,
          "md_tip" : null,
          "promotion_text" : null,
          "isdlex_free" : false,
          "sold_out_cd_yn" : null,
          "limit_age_yn" : "N",
          "link_url" : null,
          "hash_list" : [ ],
          "nint_card_flag" : "",
          "avg_gdas_stfd_val" : "0.0",
          "gdasInfo" : null,
          "save_lpoint" : 0,
          "upr_md_gsgr_no" : 0,
          "mpic_info" : null
        }, {
          "goods_no" : 393881137,
          "goods_nm" : "천안맛집 튀김소보로 호두과자 8개입",
          "brnd_nm" : "사그담",
          "curDispNo" : "",
          "flag" : "",
          "is_sale_promotion" : false,
          "img_url" : "http://image.lotte.com/goods/37/11/88/93/3/393881137_1_280.jpg",
          "img_url_550" : "http://image.lotte.com/goods/37/11/88/93/3/393881137_1_550.jpg",
          "isCrsPickYn" : false,
          "is_dept" : false,
          "isDeptPickYn" : false,
          "isDlvToday" : false,
          "isDlvQuick" : false,
          "is_himart" : false,
          "smartpick_yn" : "N",
          "is_tvhome" : false,
          "is_youngplz" : false,
          "outlnk" : null,
          "outlnkMall" : null,
          "original_price" : 0,
          "discounted_price" : 5000,
          "sale_rate" : 0,
          "is_sold_out" : false,
          "has_coupon" : false,
          "has_wish" : false,
          "review_count" : 4,
          "bought_sum" : 0,
          "find_age" : null,
          "find_gender" : null,
          "md_tip" : null,
          "promotion_text" : null,
          "isdlex_free" : false,
          "sold_out_cd_yn" : null,
          "limit_age_yn" : "N",
          "link_url" : null,
          "hash_list" : [ ],
          "nint_card_flag" : "",
          "avg_gdas_stfd_val" : "4.8",
          "gdasInfo" : null,
          "save_lpoint" : 0,
          "upr_md_gsgr_no" : 0,
          "mpic_info" : null
        }, {
          "goods_no" : 394242259,
          "goods_nm" : "[수능찹쌀떡]전주한옥마을 맛집 소부당 백미 찹쌀떡 12개입",
          "brnd_nm" : "사그담",
          "curDispNo" : "",
          "flag" : "",
          "is_sale_promotion" : false,
          "img_url" : "http://image.lotte.com/goods/59/22/24/94/3/394242259_1_280.jpg",
          "img_url_550" : "http://image.lotte.com/goods/59/22/24/94/3/394242259_1_550.jpg",
          "isCrsPickYn" : false,
          "is_dept" : false,
          "isDeptPickYn" : false,
          "isDlvToday" : false,
          "isDlvQuick" : false,
          "is_himart" : false,
          "smartpick_yn" : "N",
          "is_tvhome" : false,
          "is_youngplz" : false,
          "outlnk" : null,
          "outlnkMall" : null,
          "original_price" : 22000,
          "discounted_price" : 19900,
          "sale_rate" : 0,
          "is_sold_out" : false,
          "has_coupon" : false,
          "has_wish" : false,
          "review_count" : 0,
          "bought_sum" : 0,
          "find_age" : null,
          "find_gender" : null,
          "md_tip" : null,
          "promotion_text" : null,
          "isdlex_free" : false,
          "sold_out_cd_yn" : null,
          "limit_age_yn" : "N",
          "link_url" : null,
          "hash_list" : [ ],
          "nint_card_flag" : "",
          "avg_gdas_stfd_val" : "0.0",
          "gdasInfo" : null,
          "save_lpoint" : 0,
          "upr_md_gsgr_no" : 0,
          "mpic_info" : null
        }, {
          "goods_no" : 394294781,
          "goods_nm" : "[특별한맛남] 사르르~ 녹는다 녹아! 밥다음엔 반드시 디저트! 유명 디저트 모음",
          "brnd_nm" : "북해도 밀크팩토리",
          "curDispNo" : "",
          "flag" : "",
          "is_sale_promotion" : true,
          "img_url" : "http://image.lotte.com/goods/81/47/29/94/3/394294781_1_280.jpg",
          "img_url_550" : "http://image.lotte.com/goods/81/47/29/94/3/394294781_1_550.jpg",
          "isCrsPickYn" : false,
          "is_dept" : false,
          "isDeptPickYn" : false,
          "isDlvToday" : false,
          "isDlvQuick" : false,
          "is_himart" : false,
          "smartpick_yn" : "N",
          "is_tvhome" : false,
          "is_youngplz" : false,
          "outlnk" : null,
          "outlnkMall" : null,
          "original_price" : 34900,
          "discounted_price" : 33160,
          "sale_rate" : 0,
          "is_sold_out" : false,
          "has_coupon" : false,
          "has_wish" : false,
          "review_count" : 0,
          "bought_sum" : 0,
          "find_age" : null,
          "find_gender" : null,
          "md_tip" : null,
          "promotion_text" : null,
          "isdlex_free" : false,
          "sold_out_cd_yn" : null,
          "limit_age_yn" : "N",
          "link_url" : null,
          "hash_list" : [ ],
          "nint_card_flag" : "",
          "avg_gdas_stfd_val" : "0.0",
          "gdasInfo" : null,
          "save_lpoint" : 0,
          "upr_md_gsgr_no" : 0,
          "mpic_info" : null
        }, {
          "goods_no" : 373084452,
          "goods_nm" : "[무료배송][제주직송] 코야드 제주 수제 요구르트 150ml x 14병",
          "brnd_nm" : "코야드",
          "curDispNo" : "",
          "flag" : "",
          "is_sale_promotion" : false,
          "img_url" : "http://image.lotte.com/goods/52/44/08/73/3/373084452_1_280.jpg",
          "img_url_550" : "http://image.lotte.com/goods/52/44/08/73/3/373084452_1_550.jpg",
          "isCrsPickYn" : false,
          "is_dept" : false,
          "isDeptPickYn" : false,
          "isDlvToday" : false,
          "isDlvQuick" : false,
          "is_himart" : false,
          "smartpick_yn" : "N",
          "is_tvhome" : false,
          "is_youngplz" : false,
          "outlnk" : null,
          "outlnkMall" : null,
          "original_price" : 0,
          "discounted_price" : 35000,
          "sale_rate" : 0,
          "is_sold_out" : false,
          "has_coupon" : false,
          "has_wish" : false,
          "review_count" : 0,
          "bought_sum" : 0,
          "find_age" : null,
          "find_gender" : null,
          "md_tip" : null,
          "promotion_text" : null,
          "isdlex_free" : false,
          "sold_out_cd_yn" : null,
          "limit_age_yn" : "N",
          "link_url" : null,
          "hash_list" : [ ],
          "nint_card_flag" : "",
          "avg_gdas_stfd_val" : "0.0",
          "gdasInfo" : null,
          "save_lpoint" : 0,
          "upr_md_gsgr_no" : 0,
          "mpic_info" : null
        },  {
          "goods_no" : 396621791,
          "goods_nm" : "[경북 포항] 진짜 오징어가 들어간 오징어빵",
          "brnd_nm" : "사그담",
          "curDispNo" : "",
          "flag" : "",
          "is_sale_promotion" : false,
          "img_url" : "http://image.lotte.com/goods/91/17/62/96/3/396621791_1_280.jpg",
          "img_url_550" : "http://image.lotte.com/goods/91/17/62/96/3/396621791_1_550.jpg",
          "isCrsPickYn" : false,
          "is_dept" : false,
          "isDeptPickYn" : false,
          "isDlvToday" : false,
          "isDlvQuick" : false,
          "is_himart" : false,
          "smartpick_yn" : "N",
          "is_tvhome" : false,
          "is_youngplz" : false,
          "outlnk" : null,
          "outlnkMall" : null,
          "original_price" : 0,
          "discounted_price" : 12000,
          "sale_rate" : 0,
          "is_sold_out" : false,
          "has_coupon" : false,
          "has_wish" : false,
          "review_count" : 0,
          "bought_sum" : 0,
          "find_age" : null,
          "find_gender" : null,
          "md_tip" : null,
          "promotion_text" : null,
          "isdlex_free" : false,
          "sold_out_cd_yn" : null,
          "limit_age_yn" : "N",
          "link_url" : null,
          "hash_list" : [ ],
          "nint_card_flag" : "",
          "avg_gdas_stfd_val" : "0.0",
          "gdasInfo" : null,
          "save_lpoint" : 0,
          "upr_md_gsgr_no" : 0,
          "mpic_info" : null
        }, {
          "goods_no" : 393880992,
          "goods_nm" : "천안맛집 옛날호두과자 40개입",
          "brnd_nm" : "사그담",
          "curDispNo" : "",
          "flag" : "",
          "is_sale_promotion" : false,
          "img_url" : "http://image.lotte.com/goods/92/09/88/93/3/393880992_1_280.jpg",
          "img_url_550" : "http://image.lotte.com/goods/92/09/88/93/3/393880992_1_550.jpg",
          "isCrsPickYn" : false,
          "is_dept" : false,
          "isDeptPickYn" : false,
          "isDlvToday" : false,
          "isDlvQuick" : false,
          "is_himart" : false,
          "smartpick_yn" : "N",
          "is_tvhome" : false,
          "is_youngplz" : false,
          "outlnk" : null,
          "outlnkMall" : null,
          "original_price" : 0,
          "discounted_price" : 10000,
          "sale_rate" : 0,
          "is_sold_out" : false,
          "has_coupon" : false,
          "has_wish" : false,
          "review_count" : 0,
          "bought_sum" : 0,
          "find_age" : null,
          "find_gender" : null,
          "md_tip" : null,
          "promotion_text" : null,
          "isdlex_free" : false,
          "sold_out_cd_yn" : null,
          "limit_age_yn" : "N",
          "link_url" : null,
          "hash_list" : [ ],
          "nint_card_flag" : "",
          "avg_gdas_stfd_val" : "0.0",
          "gdasInfo" : null,
          "save_lpoint" : 0,
          "upr_md_gsgr_no" : 0,
          "mpic_info" : null
        } ]
      } ],
      "total_count" : 2
    },
    "newArrivals" : {
      "items" : [ {
          "goods_no" : 393881084,
          "goods_nm" : "천안맛집 튀김소보로 호두과자 16개입",
          "brnd_nm" : "사그담",
          "curDispNo" : "",
          "flag" : "",
          "is_sale_promotion" : false,
          "img_url" : "http://image.lotte.com/goods/84/10/88/93/3/393881084_1_280.jpg",
          "img_url_550" : "http://image.lotte.com/goods/84/10/88/93/3/393881084_1_550.jpg",
          "isCrsPickYn" : false,
          "is_dept" : false,
          "isDeptPickYn" : false,
          "isDlvToday" : false,
          "isDlvQuick" : false,
          "is_himart" : false,
          "smartpick_yn" : "N",
          "is_tvhome" : false,
          "is_youngplz" : false,
          "outlnk" : null,
          "outlnkMall" : null,
          "original_price" : 0,
          "discounted_price" : 10000,
          "sale_rate" : 0,
          "is_sold_out" : false,
          "has_coupon" : false,
          "has_wish" : false,
          "review_count" : 3,
          "bought_sum" : 0,
          "find_age" : null,
          "find_gender" : null,
          "md_tip" : null,
          "promotion_text" : null,
          "isdlex_free" : false,
          "sold_out_cd_yn" : null,
          "limit_age_yn" : "N",
          "link_url" : null,
          "hash_list" : [ ],
          "nint_card_flag" : "",
          "avg_gdas_stfd_val" : "4.7",
          "gdasInfo" : null,
          "save_lpoint" : 0,
          "upr_md_gsgr_no" : 0,
          "mpic_info" : null
        }, {
          "goods_no" : 379502213,
          "goods_nm" : "생활의 달인 그! 도담떡집의 전문 이북식인절미★ 도담떡",
          "brnd_nm" : "식탁이있는삶",
          "curDispNo" : "",
          "flag" : "",
          "is_sale_promotion" : true,
          "img_url" : "http://image.lotte.com/goods/13/22/50/79/3/379502213_2_280.jpg",
          "img_url_550" : "http://image.lotte.com/goods/13/22/50/79/3/379502213_2_550.jpg",
          "isCrsPickYn" : false,
          "is_dept" : false,
          "isDeptPickYn" : false,
          "isDlvToday" : false,
          "isDlvQuick" : false,
          "is_himart" : false,
          "smartpick_yn" : "N",
          "is_tvhome" : false,
          "is_youngplz" : false,
          "outlnk" : null,
          "outlnkMall" : null,
          "original_price" : 20000,
          "discounted_price" : 18900,
          "sale_rate" : 0,
          "is_sold_out" : false,
          "has_coupon" : false,
          "has_wish" : false,
          "review_count" : 0,
          "bought_sum" : 0,
          "find_age" : null,
          "find_gender" : null,
          "md_tip" : null,
          "promotion_text" : null,
          "isdlex_free" : false,
          "sold_out_cd_yn" : null,
          "limit_age_yn" : "N",
          "link_url" : null,
          "hash_list" : [ ],
          "nint_card_flag" : "",
          "avg_gdas_stfd_val" : "0.0",
          "gdasInfo" : null,
          "save_lpoint" : 0,
          "upr_md_gsgr_no" : 0,
          "mpic_info" : null
        }, {
          "goods_no" : 358132196,
          "goods_nm" : "국산팥100% 아이스 단팥크림빵95g 8개",
          "brnd_nm" : "소적두",
          "curDispNo" : "",
          "flag" : "",
          "is_sale_promotion" : false,
          "img_url" : "http://image.lotte.com/goods/96/21/13/58/3/358132196_1_280.jpg",
          "img_url_550" : "http://image.lotte.com/goods/96/21/13/58/3/358132196_1_550.jpg",
          "isCrsPickYn" : false,
          "is_dept" : false,
          "isDeptPickYn" : false,
          "isDlvToday" : false,
          "isDlvQuick" : false,
          "is_himart" : false,
          "smartpick_yn" : "N",
          "is_tvhome" : false,
          "is_youngplz" : false,
          "outlnk" : null,
          "outlnkMall" : null,
          "original_price" : 24500,
          "discounted_price" : 20000,
          "sale_rate" : 0,
          "is_sold_out" : false,
          "has_coupon" : false,
          "has_wish" : false,
          "review_count" : 1,
          "bought_sum" : 0,
          "find_age" : null,
          "find_gender" : null,
          "md_tip" : null,
          "promotion_text" : null,
          "isdlex_free" : false,
          "sold_out_cd_yn" : null,
          "limit_age_yn" : "N",
          "link_url" : null,
          "hash_list" : [ ],
          "nint_card_flag" : "",
          "avg_gdas_stfd_val" : "1.0",
          "gdasInfo" : null,
          "save_lpoint" : 0,
          "upr_md_gsgr_no" : 0,
          "mpic_info" : null
        }, {
          "goods_no" : 346342645,
          "goods_nm" : "[무료배송] 블루베리 크림치즈+누텔라 크림치즈+베이글 1봉지(6개입)",
          "brnd_nm" : "모노치즈",
          "curDispNo" : "",
          "flag" : "",
          "is_sale_promotion" : false,
          "img_url" : "http://image.lotte.com/goods/45/26/34/46/3/346342645_5_280.jpg",
          "img_url_550" : "http://image.lotte.com/goods/45/26/34/46/3/346342645_5_550.jpg",
          "isCrsPickYn" : false,
          "is_dept" : false,
          "isDeptPickYn" : false,
          "isDlvToday" : false,
          "isDlvQuick" : false,
          "is_himart" : false,
          "smartpick_yn" : "N",
          "is_tvhome" : false,
          "is_youngplz" : false,
          "outlnk" : null,
          "outlnkMall" : null,
          "original_price" : 0,
          "discounted_price" : 17000,
          "sale_rate" : 0,
          "is_sold_out" : false,
          "has_coupon" : false,
          "has_wish" : false,
          "review_count" : 15,
          "bought_sum" : 0,
          "find_age" : null,
          "find_gender" : null,
          "md_tip" : null,
          "promotion_text" : null,
          "isdlex_free" : false,
          "sold_out_cd_yn" : null,
          "limit_age_yn" : "N",
          "link_url" : null,
          "hash_list" : [ ],
          "nint_card_flag" : "",
          "avg_gdas_stfd_val" : "5.0",
          "gdasInfo" : null,
          "save_lpoint" : 0,
          "upr_md_gsgr_no" : 0,
          "mpic_info" : null
        }, {
          "goods_no" : 319895610,
          "goods_nm" : "1+1 골라담기 숙대명물 이상용 유기농 롤케익",
          "brnd_nm" : "크레마롤",
          "curDispNo" : "",
          "flag" : "",
          "is_sale_promotion" : false,
          "img_url" : "http://image.lotte.com/goods/10/56/89/19/3/319895610_1_280.jpg",
          "img_url_550" : "http://image.lotte.com/goods/10/56/89/19/3/319895610_1_550.jpg",
          "isCrsPickYn" : false,
          "is_dept" : false,
          "isDeptPickYn" : false,
          "isDlvToday" : false,
          "isDlvQuick" : false,
          "is_himart" : false,
          "smartpick_yn" : "N",
          "is_tvhome" : false,
          "is_youngplz" : false,
          "outlnk" : null,
          "outlnkMall" : null,
          "original_price" : 34900,
          "discounted_price" : 33160,
          "sale_rate" : 0,
          "is_sold_out" : false,
          "has_coupon" : false,
          "has_wish" : false,
          "review_count" : 38,
          "bought_sum" : 0,
          "find_age" : null,
          "find_gender" : null,
          "md_tip" : null,
          "promotion_text" : null,
          "isdlex_free" : false,
          "sold_out_cd_yn" : null,
          "limit_age_yn" : "N",
          "link_url" : null,
          "hash_list" : [ ],
          "nint_card_flag" : "",
          "avg_gdas_stfd_val" : "4.2",
          "gdasInfo" : null,
          "save_lpoint" : 0,
          "upr_md_gsgr_no" : 0,
          "mpic_info" : null
        }, {
          "goods_no" : 256588932,
          "goods_nm" : "제주도 직송! 제주 오메기떡 4종 택1",
          "brnd_nm" : "롯데식품관",
          "curDispNo" : "",
          "flag" : "",
          "is_sale_promotion" : true,
          "img_url" : "http://image.lotte.com/goods/32/89/58/56/2/256588932_1_280.jpg",
          "img_url_550" : "http://image.lotte.com/goods/32/89/58/56/2/256588932_1_550.jpg",
          "isCrsPickYn" : false,
          "is_dept" : false,
          "isDeptPickYn" : false,
          "isDlvToday" : false,
          "isDlvQuick" : false,
          "is_himart" : false,
          "smartpick_yn" : "N",
          "is_tvhome" : false,
          "is_youngplz" : false,
          "outlnk" : null,
          "outlnkMall" : null,
          "original_price" : 33900,
          "discounted_price" : 20900,
          "sale_rate" : 0,
          "is_sold_out" : false,
          "has_coupon" : false,
          "has_wish" : false,
          "review_count" : 0,
          "bought_sum" : 0,
          "find_age" : null,
          "find_gender" : null,
          "md_tip" : null,
          "promotion_text" : null,
          "isdlex_free" : false,
          "sold_out_cd_yn" : null,
          "limit_age_yn" : "N",
          "link_url" : null,
          "hash_list" : [ ],
          "nint_card_flag" : "",
          "avg_gdas_stfd_val" : "0.0",
          "gdasInfo" : null,
          "save_lpoint" : 0,
          "upr_md_gsgr_no" : 0,
          "mpic_info" : null
        },{
          "goods_no" : 393881084,
          "goods_nm" : "천안맛집 튀김소보로 호두과자 16개입",
          "brnd_nm" : "사그담",
          "curDispNo" : "",
          "flag" : "",
          "is_sale_promotion" : false,
          "img_url" : "http://image.lotte.com/goods/84/10/88/93/3/393881084_1_280.jpg",
          "img_url_550" : "http://image.lotte.com/goods/84/10/88/93/3/393881084_1_550.jpg",
          "isCrsPickYn" : false,
          "is_dept" : false,
          "isDeptPickYn" : false,
          "isDlvToday" : false,
          "isDlvQuick" : false,
          "is_himart" : false,
          "smartpick_yn" : "N",
          "is_tvhome" : false,
          "is_youngplz" : false,
          "outlnk" : null,
          "outlnkMall" : null,
          "original_price" : 0,
          "discounted_price" : 10000,
          "sale_rate" : 0,
          "is_sold_out" : false,
          "has_coupon" : false,
          "has_wish" : false,
          "review_count" : 3,
          "bought_sum" : 0,
          "find_age" : null,
          "find_gender" : null,
          "md_tip" : null,
          "promotion_text" : null,
          "isdlex_free" : false,
          "sold_out_cd_yn" : null,
          "limit_age_yn" : "N",
          "link_url" : null,
          "hash_list" : [ ],
          "nint_card_flag" : "",
          "avg_gdas_stfd_val" : "4.7",
          "gdasInfo" : null,
          "save_lpoint" : 0,
          "upr_md_gsgr_no" : 0,
          "mpic_info" : null
        }, {
          "goods_no" : 379502213,
          "goods_nm" : "생활의 달인 그! 도담떡집의 전문 이북식인절미★ 도담떡",
          "brnd_nm" : "식탁이있는삶",
          "curDispNo" : "",
          "flag" : "",
          "is_sale_promotion" : true,
          "img_url" : "http://image.lotte.com/goods/13/22/50/79/3/379502213_2_280.jpg",
          "img_url_550" : "http://image.lotte.com/goods/13/22/50/79/3/379502213_2_550.jpg",
          "isCrsPickYn" : false,
          "is_dept" : false,
          "isDeptPickYn" : false,
          "isDlvToday" : false,
          "isDlvQuick" : false,
          "is_himart" : false,
          "smartpick_yn" : "N",
          "is_tvhome" : false,
          "is_youngplz" : false,
          "outlnk" : null,
          "outlnkMall" : null,
          "original_price" : 20000,
          "discounted_price" : 18900,
          "sale_rate" : 0,
          "is_sold_out" : false,
          "has_coupon" : false,
          "has_wish" : false,
          "review_count" : 0,
          "bought_sum" : 0,
          "find_age" : null,
          "find_gender" : null,
          "md_tip" : null,
          "promotion_text" : null,
          "isdlex_free" : false,
          "sold_out_cd_yn" : null,
          "limit_age_yn" : "N",
          "link_url" : null,
          "hash_list" : [ ],
          "nint_card_flag" : "",
          "avg_gdas_stfd_val" : "0.0",
          "gdasInfo" : null,
          "save_lpoint" : 0,
          "upr_md_gsgr_no" : 0,
          "mpic_info" : null
        }, {
          "goods_no" : 358132196,
          "goods_nm" : "국산팥100% 아이스 단팥크림빵95g 8개",
          "brnd_nm" : "소적두",
          "curDispNo" : "",
          "flag" : "",
          "is_sale_promotion" : false,
          "img_url" : "http://image.lotte.com/goods/96/21/13/58/3/358132196_1_280.jpg",
          "img_url_550" : "http://image.lotte.com/goods/96/21/13/58/3/358132196_1_550.jpg",
          "isCrsPickYn" : false,
          "is_dept" : false,
          "isDeptPickYn" : false,
          "isDlvToday" : false,
          "isDlvQuick" : false,
          "is_himart" : false,
          "smartpick_yn" : "N",
          "is_tvhome" : false,
          "is_youngplz" : false,
          "outlnk" : null,
          "outlnkMall" : null,
          "original_price" : 24500,
          "discounted_price" : 20000,
          "sale_rate" : 0,
          "is_sold_out" : false,
          "has_coupon" : false,
          "has_wish" : false,
          "review_count" : 1,
          "bought_sum" : 0,
          "find_age" : null,
          "find_gender" : null,
          "md_tip" : null,
          "promotion_text" : null,
          "isdlex_free" : false,
          "sold_out_cd_yn" : null,
          "limit_age_yn" : "N",
          "link_url" : null,
          "hash_list" : [ ],
          "nint_card_flag" : "",
          "avg_gdas_stfd_val" : "1.0",
          "gdasInfo" : null,
          "save_lpoint" : 0,
          "upr_md_gsgr_no" : 0,
          "mpic_info" : null
        }, {
          "goods_no" : 346342645,
          "goods_nm" : "[무료배송] 블루베리 크림치즈+누텔라 크림치즈+베이글 1봉지(6개입)",
          "brnd_nm" : "모노치즈",
          "curDispNo" : "",
          "flag" : "",
          "is_sale_promotion" : false,
          "img_url" : "http://image.lotte.com/goods/45/26/34/46/3/346342645_5_280.jpg",
          "img_url_550" : "http://image.lotte.com/goods/45/26/34/46/3/346342645_5_550.jpg",
          "isCrsPickYn" : false,
          "is_dept" : false,
          "isDeptPickYn" : false,
          "isDlvToday" : false,
          "isDlvQuick" : false,
          "is_himart" : false,
          "smartpick_yn" : "N",
          "is_tvhome" : false,
          "is_youngplz" : false,
          "outlnk" : null,
          "outlnkMall" : null,
          "original_price" : 0,
          "discounted_price" : 17000,
          "sale_rate" : 0,
          "is_sold_out" : false,
          "has_coupon" : false,
          "has_wish" : false,
          "review_count" : 15,
          "bought_sum" : 0,
          "find_age" : null,
          "find_gender" : null,
          "md_tip" : null,
          "promotion_text" : null,
          "isdlex_free" : false,
          "sold_out_cd_yn" : null,
          "limit_age_yn" : "N",
          "link_url" : null,
          "hash_list" : [ ],
          "nint_card_flag" : "",
          "avg_gdas_stfd_val" : "5.0",
          "gdasInfo" : null,
          "save_lpoint" : 0,
          "upr_md_gsgr_no" : 0,
          "mpic_info" : null
        }, {
          "goods_no" : 319895610,
          "goods_nm" : "1+1 골라담기 숙대명물 이상용 유기농 롤케익",
          "brnd_nm" : "크레마롤",
          "curDispNo" : "",
          "flag" : "",
          "is_sale_promotion" : false,
          "img_url" : "http://image.lotte.com/goods/10/56/89/19/3/319895610_1_280.jpg",
          "img_url_550" : "http://image.lotte.com/goods/10/56/89/19/3/319895610_1_550.jpg",
          "isCrsPickYn" : false,
          "is_dept" : false,
          "isDeptPickYn" : false,
          "isDlvToday" : false,
          "isDlvQuick" : false,
          "is_himart" : false,
          "smartpick_yn" : "N",
          "is_tvhome" : false,
          "is_youngplz" : false,
          "outlnk" : null,
          "outlnkMall" : null,
          "original_price" : 34900,
          "discounted_price" : 33160,
          "sale_rate" : 0,
          "is_sold_out" : false,
          "has_coupon" : false,
          "has_wish" : false,
          "review_count" : 38,
          "bought_sum" : 0,
          "find_age" : null,
          "find_gender" : null,
          "md_tip" : null,
          "promotion_text" : null,
          "isdlex_free" : false,
          "sold_out_cd_yn" : null,
          "limit_age_yn" : "N",
          "link_url" : null,
          "hash_list" : [ ],
          "nint_card_flag" : "",
          "avg_gdas_stfd_val" : "4.2",
          "gdasInfo" : null,
          "save_lpoint" : 0,
          "upr_md_gsgr_no" : 0,
          "mpic_info" : null
        }, {
          "goods_no" : 256588932,
          "goods_nm" : "제주도 직송! 제주 오메기떡 4종 택1",
          "brnd_nm" : "롯데식품관",
          "curDispNo" : "",
          "flag" : "",
          "is_sale_promotion" : true,
          "img_url" : "http://image.lotte.com/goods/32/89/58/56/2/256588932_1_280.jpg",
          "img_url_550" : "http://image.lotte.com/goods/32/89/58/56/2/256588932_1_550.jpg",
          "isCrsPickYn" : false,
          "is_dept" : false,
          "isDeptPickYn" : false,
          "isDlvToday" : false,
          "isDlvQuick" : false,
          "is_himart" : false,
          "smartpick_yn" : "N",
          "is_tvhome" : false,
          "is_youngplz" : false,
          "outlnk" : null,
          "outlnkMall" : null,
          "original_price" : 33900,
          "discounted_price" : 20900,
          "sale_rate" : 0,
          "is_sold_out" : false,
          "has_coupon" : false,
          "has_wish" : false,
          "review_count" : 0,
          "bought_sum" : 0,
          "find_age" : null,
          "find_gender" : null,
          "md_tip" : null,
          "promotion_text" : null,
          "isdlex_free" : false,
          "sold_out_cd_yn" : null,
          "limit_age_yn" : "N",
          "link_url" : null,
          "hash_list" : [ ],
          "nint_card_flag" : "",
          "avg_gdas_stfd_val" : "0.0",
          "gdasInfo" : null,
          "save_lpoint" : 0,
          "upr_md_gsgr_no" : 0,
          "mpic_info" : null
        },{
          "goods_no" : 393881084,
          "goods_nm" : "천안맛집 튀김소보로 호두과자 16개입",
          "brnd_nm" : "사그담",
          "curDispNo" : "",
          "flag" : "",
          "is_sale_promotion" : false,
          "img_url" : "http://image.lotte.com/goods/84/10/88/93/3/393881084_1_280.jpg",
          "img_url_550" : "http://image.lotte.com/goods/84/10/88/93/3/393881084_1_550.jpg",
          "isCrsPickYn" : false,
          "is_dept" : false,
          "isDeptPickYn" : false,
          "isDlvToday" : false,
          "isDlvQuick" : false,
          "is_himart" : false,
          "smartpick_yn" : "N",
          "is_tvhome" : false,
          "is_youngplz" : false,
          "outlnk" : null,
          "outlnkMall" : null,
          "original_price" : 0,
          "discounted_price" : 10000,
          "sale_rate" : 0,
          "is_sold_out" : false,
          "has_coupon" : false,
          "has_wish" : false,
          "review_count" : 3,
          "bought_sum" : 0,
          "find_age" : null,
          "find_gender" : null,
          "md_tip" : null,
          "promotion_text" : null,
          "isdlex_free" : false,
          "sold_out_cd_yn" : null,
          "limit_age_yn" : "N",
          "link_url" : null,
          "hash_list" : [ ],
          "nint_card_flag" : "",
          "avg_gdas_stfd_val" : "4.7",
          "gdasInfo" : null,
          "save_lpoint" : 0,
          "upr_md_gsgr_no" : 0,
          "mpic_info" : null
        }, {
          "goods_no" : 379502213,
          "goods_nm" : "생활의 달인 그! 도담떡집의 전문 이북식인절미★ 도담떡",
          "brnd_nm" : "식탁이있는삶",
          "curDispNo" : "",
          "flag" : "",
          "is_sale_promotion" : true,
          "img_url" : "http://image.lotte.com/goods/13/22/50/79/3/379502213_2_280.jpg",
          "img_url_550" : "http://image.lotte.com/goods/13/22/50/79/3/379502213_2_550.jpg",
          "isCrsPickYn" : false,
          "is_dept" : false,
          "isDeptPickYn" : false,
          "isDlvToday" : false,
          "isDlvQuick" : false,
          "is_himart" : false,
          "smartpick_yn" : "N",
          "is_tvhome" : false,
          "is_youngplz" : false,
          "outlnk" : null,
          "outlnkMall" : null,
          "original_price" : 20000,
          "discounted_price" : 18900,
          "sale_rate" : 0,
          "is_sold_out" : false,
          "has_coupon" : false,
          "has_wish" : false,
          "review_count" : 0,
          "bought_sum" : 0,
          "find_age" : null,
          "find_gender" : null,
          "md_tip" : null,
          "promotion_text" : null,
          "isdlex_free" : false,
          "sold_out_cd_yn" : null,
          "limit_age_yn" : "N",
          "link_url" : null,
          "hash_list" : [ ],
          "nint_card_flag" : "",
          "avg_gdas_stfd_val" : "0.0",
          "gdasInfo" : null,
          "save_lpoint" : 0,
          "upr_md_gsgr_no" : 0,
          "mpic_info" : null
        }, {
          "goods_no" : 358132196,
          "goods_nm" : "국산팥100% 아이스 단팥크림빵95g 8개",
          "brnd_nm" : "소적두",
          "curDispNo" : "",
          "flag" : "",
          "is_sale_promotion" : false,
          "img_url" : "http://image.lotte.com/goods/96/21/13/58/3/358132196_1_280.jpg",
          "img_url_550" : "http://image.lotte.com/goods/96/21/13/58/3/358132196_1_550.jpg",
          "isCrsPickYn" : false,
          "is_dept" : false,
          "isDeptPickYn" : false,
          "isDlvToday" : false,
          "isDlvQuick" : false,
          "is_himart" : false,
          "smartpick_yn" : "N",
          "is_tvhome" : false,
          "is_youngplz" : false,
          "outlnk" : null,
          "outlnkMall" : null,
          "original_price" : 24500,
          "discounted_price" : 20000,
          "sale_rate" : 0,
          "is_sold_out" : false,
          "has_coupon" : false,
          "has_wish" : false,
          "review_count" : 1,
          "bought_sum" : 0,
          "find_age" : null,
          "find_gender" : null,
          "md_tip" : null,
          "promotion_text" : null,
          "isdlex_free" : false,
          "sold_out_cd_yn" : null,
          "limit_age_yn" : "N",
          "link_url" : null,
          "hash_list" : [ ],
          "nint_card_flag" : "",
          "avg_gdas_stfd_val" : "1.0",
          "gdasInfo" : null,
          "save_lpoint" : 0,
          "upr_md_gsgr_no" : 0,
          "mpic_info" : null
        }, {
          "goods_no" : 346342645,
          "goods_nm" : "[무료배송] 블루베리 크림치즈+누텔라 크림치즈+베이글 1봉지(6개입)",
          "brnd_nm" : "모노치즈",
          "curDispNo" : "",
          "flag" : "",
          "is_sale_promotion" : false,
          "img_url" : "http://image.lotte.com/goods/45/26/34/46/3/346342645_5_280.jpg",
          "img_url_550" : "http://image.lotte.com/goods/45/26/34/46/3/346342645_5_550.jpg",
          "isCrsPickYn" : false,
          "is_dept" : false,
          "isDeptPickYn" : false,
          "isDlvToday" : false,
          "isDlvQuick" : false,
          "is_himart" : false,
          "smartpick_yn" : "N",
          "is_tvhome" : false,
          "is_youngplz" : false,
          "outlnk" : null,
          "outlnkMall" : null,
          "original_price" : 0,
          "discounted_price" : 17000,
          "sale_rate" : 0,
          "is_sold_out" : false,
          "has_coupon" : false,
          "has_wish" : false,
          "review_count" : 15,
          "bought_sum" : 0,
          "find_age" : null,
          "find_gender" : null,
          "md_tip" : null,
          "promotion_text" : null,
          "isdlex_free" : false,
          "sold_out_cd_yn" : null,
          "limit_age_yn" : "N",
          "link_url" : null,
          "hash_list" : [ ],
          "nint_card_flag" : "",
          "avg_gdas_stfd_val" : "5.0",
          "gdasInfo" : null,
          "save_lpoint" : 0,
          "upr_md_gsgr_no" : 0,
          "mpic_info" : null
        }, {
          "goods_no" : 319895610,
          "goods_nm" : "1+1 골라담기 숙대명물 이상용 유기농 롤케익",
          "brnd_nm" : "크레마롤",
          "curDispNo" : "",
          "flag" : "",
          "is_sale_promotion" : false,
          "img_url" : "http://image.lotte.com/goods/10/56/89/19/3/319895610_1_280.jpg",
          "img_url_550" : "http://image.lotte.com/goods/10/56/89/19/3/319895610_1_550.jpg",
          "isCrsPickYn" : false,
          "is_dept" : false,
          "isDeptPickYn" : false,
          "isDlvToday" : false,
          "isDlvQuick" : false,
          "is_himart" : false,
          "smartpick_yn" : "N",
          "is_tvhome" : false,
          "is_youngplz" : false,
          "outlnk" : null,
          "outlnkMall" : null,
          "original_price" : 34900,
          "discounted_price" : 33160,
          "sale_rate" : 0,
          "is_sold_out" : false,
          "has_coupon" : false,
          "has_wish" : false,
          "review_count" : 38,
          "bought_sum" : 0,
          "find_age" : null,
          "find_gender" : null,
          "md_tip" : null,
          "promotion_text" : null,
          "isdlex_free" : false,
          "sold_out_cd_yn" : null,
          "limit_age_yn" : "N",
          "link_url" : null,
          "hash_list" : [ ],
          "nint_card_flag" : "",
          "avg_gdas_stfd_val" : "4.2",
          "gdasInfo" : null,
          "save_lpoint" : 0,
          "upr_md_gsgr_no" : 0,
          "mpic_info" : null
        }, {
          "goods_no" : 256588932,
          "goods_nm" : "제주도 직송! 제주 오메기떡 4종 택1",
          "brnd_nm" : "롯데식품관",
          "curDispNo" : "",
          "flag" : "",
          "is_sale_promotion" : true,
          "img_url" : "http://image.lotte.com/goods/32/89/58/56/2/256588932_1_280.jpg",
          "img_url_550" : "http://image.lotte.com/goods/32/89/58/56/2/256588932_1_550.jpg",
          "isCrsPickYn" : false,
          "is_dept" : false,
          "isDeptPickYn" : false,
          "isDlvToday" : false,
          "isDlvQuick" : false,
          "is_himart" : false,
          "smartpick_yn" : "N",
          "is_tvhome" : false,
          "is_youngplz" : false,
          "outlnk" : null,
          "outlnkMall" : null,
          "original_price" : 33900,
          "discounted_price" : 20900,
          "sale_rate" : 0,
          "is_sold_out" : false,
          "has_coupon" : false,
          "has_wish" : false,
          "review_count" : 0,
          "bought_sum" : 0,
          "find_age" : null,
          "find_gender" : null,
          "md_tip" : null,
          "promotion_text" : null,
          "isdlex_free" : false,
          "sold_out_cd_yn" : null,
          "limit_age_yn" : "N",
          "link_url" : null,
          "hash_list" : [ ],
          "nint_card_flag" : "",
          "avg_gdas_stfd_val" : "0.0",
          "gdasInfo" : null,
          "save_lpoint" : 0,
          "upr_md_gsgr_no" : 0,
          "mpic_info" : null
        } ],
      "total_count" : 2
    },
    "best" : {
      "items" : [{
          "goods_no" : 393881084,
          "goods_nm" : "천안맛집 튀김소보로 호두과자 16개입",
          "brnd_nm" : "사그담",
          "curDispNo" : "",
          "flag" : "",
          "is_sale_promotion" : false,
          "img_url" : "http://image.lotte.com/goods/84/10/88/93/3/393881084_1_280.jpg",
          "img_url_550" : "http://image.lotte.com/goods/84/10/88/93/3/393881084_1_550.jpg",
          "isCrsPickYn" : false,
          "is_dept" : false,
          "isDeptPickYn" : false,
          "isDlvToday" : false,
          "isDlvQuick" : false,
          "is_himart" : false,
          "smartpick_yn" : "N",
          "is_tvhome" : false,
          "is_youngplz" : false,
          "outlnk" : null,
          "outlnkMall" : null,
          "original_price" : 0,
          "discounted_price" : 10000,
          "sale_rate" : 0,
          "is_sold_out" : false,
          "has_coupon" : false,
          "has_wish" : false,
          "review_count" : 3,
          "bought_sum" : 0,
          "find_age" : null,
          "find_gender" : null,
          "md_tip" : null,
          "promotion_text" : null,
          "isdlex_free" : false,
          "sold_out_cd_yn" : null,
          "limit_age_yn" : "N",
          "link_url" : null,
          "hash_list" : [ ],
          "nint_card_flag" : "",
          "avg_gdas_stfd_val" : "4.7",
          "gdasInfo" : null,
          "save_lpoint" : 0,
          "upr_md_gsgr_no" : 0,
          "mpic_info" : null
        }, {
          "goods_no" : 379502213,
          "goods_nm" : "생활의 달인 그! 도담떡집의 전문 이북식인절미★ 도담떡",
          "brnd_nm" : "식탁이있는삶",
          "curDispNo" : "",
          "flag" : "",
          "is_sale_promotion" : true,
          "img_url" : "http://image.lotte.com/goods/13/22/50/79/3/379502213_2_280.jpg",
          "img_url_550" : "http://image.lotte.com/goods/13/22/50/79/3/379502213_2_550.jpg",
          "isCrsPickYn" : false,
          "is_dept" : false,
          "isDeptPickYn" : false,
          "isDlvToday" : false,
          "isDlvQuick" : false,
          "is_himart" : false,
          "smartpick_yn" : "N",
          "is_tvhome" : false,
          "is_youngplz" : false,
          "outlnk" : null,
          "outlnkMall" : null,
          "original_price" : 20000,
          "discounted_price" : 18900,
          "sale_rate" : 0,
          "is_sold_out" : false,
          "has_coupon" : false,
          "has_wish" : false,
          "review_count" : 0,
          "bought_sum" : 0,
          "find_age" : null,
          "find_gender" : null,
          "md_tip" : null,
          "promotion_text" : null,
          "isdlex_free" : false,
          "sold_out_cd_yn" : null,
          "limit_age_yn" : "N",
          "link_url" : null,
          "hash_list" : [ ],
          "nint_card_flag" : "",
          "avg_gdas_stfd_val" : "0.0",
          "gdasInfo" : null,
          "save_lpoint" : 0,
          "upr_md_gsgr_no" : 0,
          "mpic_info" : null
        }, {
          "goods_no" : 358132196,
          "goods_nm" : "국산팥100% 아이스 단팥크림빵95g 8개",
          "brnd_nm" : "소적두",
          "curDispNo" : "",
          "flag" : "",
          "is_sale_promotion" : false,
          "img_url" : "http://image.lotte.com/goods/96/21/13/58/3/358132196_1_280.jpg",
          "img_url_550" : "http://image.lotte.com/goods/96/21/13/58/3/358132196_1_550.jpg",
          "isCrsPickYn" : false,
          "is_dept" : false,
          "isDeptPickYn" : false,
          "isDlvToday" : false,
          "isDlvQuick" : false,
          "is_himart" : false,
          "smartpick_yn" : "N",
          "is_tvhome" : false,
          "is_youngplz" : false,
          "outlnk" : null,
          "outlnkMall" : null,
          "original_price" : 24500,
          "discounted_price" : 20000,
          "sale_rate" : 0,
          "is_sold_out" : false,
          "has_coupon" : false,
          "has_wish" : false,
          "review_count" : 1,
          "bought_sum" : 0,
          "find_age" : null,
          "find_gender" : null,
          "md_tip" : null,
          "promotion_text" : null,
          "isdlex_free" : false,
          "sold_out_cd_yn" : null,
          "limit_age_yn" : "N",
          "link_url" : null,
          "hash_list" : [ ],
          "nint_card_flag" : "",
          "avg_gdas_stfd_val" : "1.0",
          "gdasInfo" : null,
          "save_lpoint" : 0,
          "upr_md_gsgr_no" : 0,
          "mpic_info" : null
        }, {
          "goods_no" : 346342645,
          "goods_nm" : "[무료배송] 블루베리 크림치즈+누텔라 크림치즈+베이글 1봉지(6개입)",
          "brnd_nm" : "모노치즈",
          "curDispNo" : "",
          "flag" : "",
          "is_sale_promotion" : false,
          "img_url" : "http://image.lotte.com/goods/45/26/34/46/3/346342645_5_280.jpg",
          "img_url_550" : "http://image.lotte.com/goods/45/26/34/46/3/346342645_5_550.jpg",
          "isCrsPickYn" : false,
          "is_dept" : false,
          "isDeptPickYn" : false,
          "isDlvToday" : false,
          "isDlvQuick" : false,
          "is_himart" : false,
          "smartpick_yn" : "N",
          "is_tvhome" : false,
          "is_youngplz" : false,
          "outlnk" : null,
          "outlnkMall" : null,
          "original_price" : 0,
          "discounted_price" : 17000,
          "sale_rate" : 0,
          "is_sold_out" : false,
          "has_coupon" : false,
          "has_wish" : false,
          "review_count" : 15,
          "bought_sum" : 0,
          "find_age" : null,
          "find_gender" : null,
          "md_tip" : null,
          "promotion_text" : null,
          "isdlex_free" : false,
          "sold_out_cd_yn" : null,
          "limit_age_yn" : "N",
          "link_url" : null,
          "hash_list" : [ ],
          "nint_card_flag" : "",
          "avg_gdas_stfd_val" : "5.0",
          "gdasInfo" : null,
          "save_lpoint" : 0,
          "upr_md_gsgr_no" : 0,
          "mpic_info" : null
        }, {
          "goods_no" : 319895610,
          "goods_nm" : "1+1 골라담기 숙대명물 이상용 유기농 롤케익",
          "brnd_nm" : "크레마롤",
          "curDispNo" : "",
          "flag" : "",
          "is_sale_promotion" : false,
          "img_url" : "http://image.lotte.com/goods/10/56/89/19/3/319895610_1_280.jpg",
          "img_url_550" : "http://image.lotte.com/goods/10/56/89/19/3/319895610_1_550.jpg",
          "isCrsPickYn" : false,
          "is_dept" : false,
          "isDeptPickYn" : false,
          "isDlvToday" : false,
          "isDlvQuick" : false,
          "is_himart" : false,
          "smartpick_yn" : "N",
          "is_tvhome" : false,
          "is_youngplz" : false,
          "outlnk" : null,
          "outlnkMall" : null,
          "original_price" : 34900,
          "discounted_price" : 33160,
          "sale_rate" : 0,
          "is_sold_out" : false,
          "has_coupon" : false,
          "has_wish" : false,
          "review_count" : 38,
          "bought_sum" : 0,
          "find_age" : null,
          "find_gender" : null,
          "md_tip" : null,
          "promotion_text" : null,
          "isdlex_free" : false,
          "sold_out_cd_yn" : null,
          "limit_age_yn" : "N",
          "link_url" : null,
          "hash_list" : [ ],
          "nint_card_flag" : "",
          "avg_gdas_stfd_val" : "4.2",
          "gdasInfo" : null,
          "save_lpoint" : 0,
          "upr_md_gsgr_no" : 0,
          "mpic_info" : null
        }, {
          "goods_no" : 256588932,
          "goods_nm" : "제주도 직송! 제주 오메기떡 4종 택1",
          "brnd_nm" : "롯데식품관",
          "curDispNo" : "",
          "flag" : "",
          "is_sale_promotion" : true,
          "img_url" : "http://image.lotte.com/goods/32/89/58/56/2/256588932_1_280.jpg",
          "img_url_550" : "http://image.lotte.com/goods/32/89/58/56/2/256588932_1_550.jpg",
          "isCrsPickYn" : false,
          "is_dept" : false,
          "isDeptPickYn" : false,
          "isDlvToday" : false,
          "isDlvQuick" : false,
          "is_himart" : false,
          "smartpick_yn" : "N",
          "is_tvhome" : false,
          "is_youngplz" : false,
          "outlnk" : null,
          "outlnkMall" : null,
          "original_price" : 33900,
          "discounted_price" : 20900,
          "sale_rate" : 0,
          "is_sold_out" : false,
          "has_coupon" : false,
          "has_wish" : false,
          "review_count" : 0,
          "bought_sum" : 0,
          "find_age" : null,
          "find_gender" : null,
          "md_tip" : null,
          "promotion_text" : null,
          "isdlex_free" : false,
          "sold_out_cd_yn" : null,
          "limit_age_yn" : "N",
          "link_url" : null,
          "hash_list" : [ ],
          "nint_card_flag" : "",
          "avg_gdas_stfd_val" : "0.0",
          "gdasInfo" : null,
          "save_lpoint" : 0,
          "upr_md_gsgr_no" : 0,
          "mpic_info" : null
      } ],
      "total_count" : 2
    },
    "pinterest" : {
      "title":"식품MD의 추천 콘텐츠",
      "items" : [{
        "txt" : "해피 크리스마스 기프트 대전!",
        "imgUrl" : "http://image.lotte.com/goods/70/50/95/76/1/176955070_1_280.jpg",
        "setNo" : "5243230"
      }, {
        "txt" : "샤넬, 홀리데이 기념 온라인 단독",
        "imgUrl" : "http://image.lotte.com/goods/23/57/94/53/4/453945723_1_280.jpg",
        "setNo" : "5411870"
      }, {
        "txt" : "SK-II 피테라 에센스 리미티드 에디션",
        "imgUrl" : "http://image.lotte.com/goods/66/39/23/56/4/456233966_2_280.gif",
        "setNo" : "1722588"
      },{
        "txt" : "[한율] 어린쑥 수분진정 크림 50ml",
        "imgUrl" : "http://image.lotte.com/goods/66/39/23/56/4/456233966_2_280.gif",
        "setNo" : "1722588"
      }],
      "total_count" : 4
    }
  }
}